Workbook

Sheet Sprint Plan
A2: Due Date | B2: Responsible | C2: Task | E2: Status
A3: EOD 11/1 | B3: KMT | C3: SJE Record Structure | E3: Done
A4: EOD 11/1 | B4: KMT | C4: IP Record Structure | E4: Done
A5: EOD 11/1 | B5: KMT | C5: SAL Record Structure | E5: Done
A6: EOD 11/1 | B6: KMT | C6: Audit Record Structure | E6: Passed
A7: EOD 11/1 | B7: KMT | C7: Consider COGS Account Usage | E7: Done
A8: EOD 11/1 | B8: KMT | C8: Can we make use of non-matched PO records | E8: Done
A9: EOD 11/4 | B9: Rajan | C9: Import Record Structures | E9: Done
A10: EOD 11/4 | B10: Rajan | C10: Prepare Rev Records with new IP Designations using the Revenue IP SS | E10: Done
A11: EOD 11/7 | B11: Rajan | C11: Add 2 new SAL fields | E11: Done
A12: EOD 11/7 | B12: Rajan | C12: Update COA Structures | E12: Done
A13: EOD 11/7 | B13: Rajan | C13: Import the new reference files | E13: Done
D14: COA | E14: Done
D15: COA_ACCOUNT_TYPE | E15: Done
D16: COA_CLASS_CODE | E16: Done
D17: COA_LEDGER_TYPE | E17: Done
A18: EOD 11/7 | B18: Rajan | C18: Create Rules | E18: Done
C19: a | D19: PO sent, reflects Commitment, | E19: Done
C20: b | D20: Inventory received, payable recognized | E20: Done
C21: c | D21: Invoice received for services, expenses recognized | E21: Done
C22: d | D22: Pay invoices for services (can be combined with event type e) | E22: Done
C23: e | D23: Pay invoices for goods (can be combined with event d) | E23: Done
C24: f | D24: Pay for other invoices | E24: Done
C25: g | D25: Sale goods (inv reduction, expense recognized) | E25: Done
C26: h | D26: Tax Receipts (including sales of goods) | E26: Done
A27: EOD 11/18 | B27: Rajan | C27: Prepare two years of data in PO, Payment and Rev Files
A28: EOD 11/18 | B28: Kip/Rajan | C28: Load 1 year of data to platform | E28: Done
A29: EOD 11/18 | B29: Kip | C29: Verify Statistics about the Data | E29: Done | Q29: i | S29: Year-end
D30: count of vendors with no POs | E30: Done
D31: total amount spent on Vendor w and w/o PO | E31: Done
D32: Count of vendors with some POs, but <> in total payment | E32: Done
D33: Total rev vs. total expense for year | E33: Done
D34: Verify ending balances per Account Type per T Account | E34: Done
D35: (For example no inventory balances at end of year) | E35: Done
A36: EOD 11/19 | B36: Kip | C36: Define Year End Rules | E36: Done
A37: EOD 11/19 | B37: Kip/Rajan | C37: Process two years of data in PO, Payment and Rev Files on the platform
D38: Show comparison Reports for year to year
D39: Using same stats as above
A42: December Sprint
A43: EDO 12/6 | B43: Rajan | C43: Record Video
A44: EDO 12/11 | B44: Kip | C44: Video Edited, Voice Over
A45: 43803 | B45: Kip | C45: Upload 2017 data to data world | E45: Done
A46: 43803 | B46: Rajan | C46: Write program to verify file structure | E46: Done
A47: 43804 | B47: Kip/Rajan/Rakesh | C47: Verify SAL assignments specs | E47: Deferred
A48: 43806 | B48: Kip | C48: Budget T- Accounts | E48: Done
A49: 43806 | B49: Kip | C49: Updated SAL Definitions | E49: Deferred
A50: 43808 | B50: Rajan | C50: Test values against reference data to get (1) list of not found, (2) % found vs NF | E50: Done
A51: 43808 | B51: Rajan | C51: Suspense/Rejject Functionality Discussion Processing | E51: Done
A52: 43809 | B52: Rajan | C52: Assign Dummy Values to all Reference Files | E52: Done
A53: 43810 | B53: Kip/Rajan | C53: Define Accounting Rules with Reverse Lookup for codes | E53: Done
A54: 43810 | B54: Rajan | C54: Run pre-processes against 2017 - 2018 data | E54: Done
A55: 43811 | B55: Rajan | C55: Preliminary SAL Review | E55: Done
A56: 43812 | B56: Kip | C56: Get new NIGP Codes | E56: Done
A57: 43823 | B57: Kip/Rajan | C57: Discussed changes in record formats for new years, developed append plan when needed | E57: Done
A58: 43814 | B58: Kip/Rajan | C58: Actual Processing
A59: 43814 | B59: Kip/Rajan | C59: Verify Reports
A60: 43814 | B60: Kip/Rajan | C60: Review SAL definition
A61: 43815 | B61: Rajan | C61: Video 2017 Data | G61: 2017 Data | I61: 2017-2003 Name CR | L61: 2003 Source Name to 2003 SRC_SOURCE_CODE | O61: 2003 Refernce File
G62: Source Name 2017 | I62: Source Name 2017 | J62: Source Name 2003 | L62: Source Name 2003 | M62: SRC_SOURCE_CODE | O62: SRC_SOURCE_CODE | P62: hierarchy, etc….
A63: Goal Sprint | B63: December End | C63: Sprint Ends Dec 23
C64: Request IBM Cloud environment
C65: Year-end Processing, 2017 (also load 2018 data)
C66: Processing 2017 Data, and design suspense/reject outputs
D67: Specify Suspense value if suspense selected
D68: Specify if file or record should be reject if reject is selected
C69: Processing 2017 Budget vs Actual
C70: Local install of platform
C71: Demo's given to
D72: David Paget-Brown
D73: David Turner/John Waterman
D74: Ewan Pucle Hobbs, in Asia
D75: Zion's Bank controller
D76: Steve Turner, Bay Area Consultant
D77: Investigate Virginia Contact
D78: David Paget-Brown VA Contact
D79: Scott Prophet?
C80: Close Initial Sale Commitment from Rick Roth
C81: Mexico Contact
C82: Business Purpose Slides Deck/Video to introduce Demo

Sheet T Accounts Early
B2: Expense Accounts | K2: Revenue | T2: Files
E3: (Various Detailed Accounts from Object Table) | N3: (Various Detailed Accounts from Source Table)
C4: File | D4: Arrg | L4: File | M4: Arrg | P4: File | Q4: Arrg | T4: 1 | U4: POs Matched and Unmatched with NIGP <900
B5: c | C5: 3 | D5: S | E5: Services received | F5: i | G5: 7 | H5: G | I5: Year End Closeout | K5: i | L5: 7 | M5: G | N5: Year End Closeout | O5: h | P5: 6 | Q5: R | R5: Tax reiiepts, goods sold | T5: 2 | U5: POs with Matched payments with NIGP <900
B6: f | C6: 5 | D6: O | E6: pay other invoices | T6: 3 | U6: Payments with Matched PO with NIGP > 900
B7: g | C7: 4 | D7: E | E7: cost of inv sold | T7: 4 | U7: Payments with Matched PO with NIGP<900
T8: 5 | U8: Payments without Matched PO
B9: Accounts Payable | K9: Cash | T9: 6 | U9: Revenue received
C10: File | D10: Arrg | G10: File | L10: File | M10: Arrg | N10: =CofA!C6 -> 1010001 | P10: File | Q10: Arrg | T10: 7 | U10: New Record | V10: Year End
B11: d | C11: 3 | D11: P | E11: pay services invoices | F11: b | G11: 2 | H11: P | I11: Inv received | K11: h | L11: 6 | M11: G | N11: Tax receipts, goods sold | O11: d | P11: 3 | Q11: G | R11: pay services invoices | T11: 8 | U11: Initial Arrangement Data
B12: e | C12: 4 | D12: P | E12: pay inv. Invoices | F12: c | G12: 3 | H12: S | I12: Services received | O12: e | P12: 4 | Q12: G | R12: pay inv. Invoices | T12: Arrangement
O13: f | P13: 5 | Q13: G | R13: pay other invoices | T13: I | U13: Inventory | V13: Inventory attributes, IP = State of VA, "PO All" (Removed PO dates on SAL, use NIGP as Arrangement ID?)
T14: C | U14: Commit | V14: IP = Vendor, "PO All"
T15: P | U15: PO,Pay | V15: IP = Vendor, "PO With Payment"
B16: Inventory Receivable (Commitment Account) | K16: Commitments Payable (Commitment Account) | T16: S | U16: Services | V16: Inventory = Services, IP = Vendor, "Payment With PO"
C17: File | D17: Arrg | G17: File | L17: File | M17: Arrg | N17: =CofA!C22 -> 2010151 | P17: File | Q17: Arrg | T17: R | U17: Revenue | V17: IP = Rev IP, "Taxes"
B18: a | C18: 1 | D18: I | E18: PO Setn for Inv | O18: a | P18: 1 | Q18: C | R18: PO Setn for Inv | T18: G | U18: Generic | V18: IP=State of VA
F19: b | G19: 2 | H19: I | I19: Inv received | K19: b | L19: 2 | M19: P | N19: Inv received | T19: E | U19: Exp Inv | V19: Inventory attributes, IP = Vendor, "Payment with PO"
T20: O | U20: Exp Other | V20: IP = Vendor, "Payment W/O PO"
B22: Inventory - Finished Goods (Financial Account) | K22: Fund | T22: Entry | U22: Event Code
B23: b | C23: 2 | D23: I | E23: Inv Received | F23: g | G23: 4 | H23: I | I23: cost of inv sold | L23: File | M23: Arrg | N23: 3010001 | P23: File | Q23: Arrg | U23: EV00 | V23: Initialize Arrangement Data
K24: i | L24: 7 | M24: G | N24: Year End Closeout | O24: i | P24: 7 | Q24: G | R24: Year End Closeout | T24: a | U24: EV01 | V24: PO sent, reflects Commitment, Non Fin Transaction, Ledger = CMT
T25: b | U25: EV02 | V25: Inventory received, payable recognized Ledger = FIN
B26: Asset Account (BUDGET) | K26: Expense Account (use Undefined Expense) | T26: c | U26: EV03 | V26: Invoice received for services, expenses recognized, Ledger = FIN
C27: File | D27: Arrg | E27: 1090001 | G27: File | H27: Arrg | L27: File | M27: Arrg | N27: 4000000 | P27: File | Q27: Arrg | T27: d | U27: EV04 | V27: Pay invoices for services (can be combined with event type e, file is only different)
T28: e | V28: Pay invoices for goods (can be combined with event d, only file is different)
T29: g | U29: EV06 | V29: Sale goods (inv reduction, expense recognized)
K30: Fund Account | T30: h | U30: EV07 | V30: Tax Receipts (including sales of goods)
L31: File | M31: Arrg | N31: 3010003 | P31: File | Q31: Arrg | T31: i | U31: EV08 | V31: Year-end

Sheet T Accounts Early 2016
B2: Expense Accounts | K2: Revenue | T2: Files
E3: (Various Detailed Accounts from Object Table) | N3: (Various Detailed Accounts from Source Table)
C4: File | D4: Arrg | L4: File | M4: Arrg | P4: File | Q4: Arrg | T4: 1 | U4: POs Matched and Unmatched with NIGP <9000
B5: c | C5: 3 | D5: S | E5: Services received | F5: i | G5: 7 | H5: G | I5: Year End Closeout | K5: i | L5: 7 | M5: G | N5: Year End Closeout | O5: h | P5: 6 | Q5: R | R5: Tax reiiepts, goods sold | T5: 2 | U5: POs with Matched payments with NIGP <9000
B6: f | C6: 5 | D6: O | E6: pay other invoices | T6: 3 | U6: Payments with Matched PO with NIGP > 9000
B7: g | C7: 4 | D7: E | E7: cost of inv sold | T7: 4 | U7: Payments with Matched PO with NIGP<9000
T8: 5 | U8: Payments without Matched PO
B9: Accounts Payable | K9: Cash | T9: 6 | U9: Revenue received
C10: File | D10: Arrg | G10: File | L10: File | M10: Arrg | N10: =CofA!C6 -> 1010001 | P10: File | Q10: Arrg | T10: 7 | U10: New Record | V10: Year End
B11: d | C11: 3 | D11: P | E11: pay services invoices | F11: b | G11: 2 | H11: P | I11: Inv received | K11: h | L11: 6 | M11: G | N11: Tax receipts, goods sold | O11: d | P11: 3 | Q11: G | R11: pay services invoices | T11: 8 | U11: Initial Arrangement Data
B12: e | C12: 4 | D12: P | E12: pay inv. Invoices | F12: c | G12: 3 | H12: S | I12: Services received | O12: e | P12: 4 | Q12: G | R12: pay inv. Invoices | T12: Arrangement
O13: f | P13: 5 | Q13: G | R13: pay other invoices | T13: I | U13: Inventory | V13: Inventory attributes, IP = State of VA, "PO All" (Removed PO dates on SAL, use NIGP as Arrangement ID?)
T14: C | U14: Commit | V14: IP = Vendor, "PO All"
T15: P | U15: PO,Pay | V15: IP = Vendor, "PO With Payment"
B16: Inventory Receivable (Commitment Account) | K16: Commitments Payable (Commitment Account) | T16: S | U16: Services | V16: Inventory = Services, IP = Vendor, "Payment With PO"
C17: File | D17: Arrg | G17: File | L17: File | M17: Arrg | N17: =CofA!C22 -> 2010151 | P17: File | Q17: Arrg | T17: R | U17: Revenue | V17: IP = Rev IP, "Taxes"
B18: a | C18: 1 | D18: I | E18: PO Setn for Inv | O18: a | P18: 1 | Q18: C | R18: PO Setn for Inv | T18: G | U18: Generic | V18: IP=State of VA
F19: b | G19: 2 | H19: I | I19: Inv received | K19: b | L19: 2 | M19: P | N19: Inv received | T19: E | U19: Exp Inv | V19: Inventory attributes, IP = Vendor, "Payment with PO"
T20: O | U20: Exp Other | V20: IP = Vendor, "Payment W/O PO"
B22: Inventory - Finished Goods (Financial Account) | K22: Fund | T22: Entry | U22: Event Code
B23: b | C23: 2 | D23: I | E23: Inv Received | F23: g | G23: 4 | H23: I | I23: cost of inv sold | L23: File | M23: Arrg | N23: 3010001 | P23: File | Q23: Arrg | U23: EV00 | V23: Initialize Arrangement Data
K24: i | L24: 7 | M24: G | N24: Year End Closeout | O24: i | P24: 7 | Q24: G | R24: Year End Closeout | T24: a | U24: EV01 | V24: PO sent, reflects Commitment, Non Fin Transaction, Ledger = CMT
T25: b | U25: EV02 | V25: Inventory received, payable recognized Ledger = FIN
B26: Asset Account (BUDGET) | K26: Expense Account (use Undefined Expense) | T26: c | U26: EV03 | V26: Invoice received for services, expenses recognized, Ledger = FIN
C27: File | D27: Arrg | E27: 1090001 | G27: File | H27: Arrg | L27: File | M27: Arrg | N27: 4000000 | P27: File | Q27: Arrg | T27: d | U27: EV04 | V27: Pay invoices for services (can be combined with event type e, file is only different)
T28: e | V28: Pay invoices for goods (can be combined with event d, only file is different)
T29: g | U29: EV06 | V29: Sale goods (inv reduction, expense recognized)
K30: Fund Account | T30: h | U30: EV07 | V30: Tax Receipts (including sales of goods)
L31: File | M31: Arrg | N31: 3010003 | P31: File | Q31: Arrg | T31: i | U31: EV08 | V31: Year-end

Sheet T Accounts 2017
B2: Expense Accounts | K2: Revenue | T2: Files
E3: (Various Detailed Accounts from Object Table) | N3: (Various Detailed Accounts from Source Table)
C4: File | D4: Arrg | L4: File | M4: Arrg | P4: File | Q4: Arrg | T4: 1 | U4: All POs
B5: d | C5: 5 | D5: G | E5: Inv/Services Received | F5: i | G5: 7 | H5: G | I5: Year End Closeout | K5: i | L5: 7 | M5: G | N5: Year End Closeout | O5: h | P5: 6 | Q5: R | R5: Tax reiiepts, goods sold | T5: 2
T6: 3
T7: 4
T8: 5 | U8: Payments without Matched PO (All Payments)
B9: Accounts Payable | K9: Cash | T9: 6 | U9: Revenue received
C10: File | D10: Arrg | G10: File | L10: File | M10: Arrg | N10: =CofA!C6 -> 1010001 | P10: File | Q10: Arrg | T10: 7 | U10: New Record | V10: Year End
B11: d | C11: 5 | D11: G | E11: pay all invoices | F11: a | G11: 1 | H11: C | I11: PO sent to Vendor | K11: h | L11: 6 | M11: G | N11: Tax receipts, goods sold | O11: d | P11: 5 | Q11: G | R11: pay all invoices | T11: 8 | U11: Budget file
T12: Arrangement
T13: I
T14: C | U14: Commit | V14: IP = Vendor, "PO All"
T15: P
B16: Inventory Receivable (FIN Account) | K16: Commitments Payable (Commitment Account) | T16: S
C17: File | D17: Arrg | G17: File | L17: File | M17: Arrg | N17: =CofA!C22 -> 2010151 | P17: File | Q17: Arrg | T17: R | U17: Revenue | V17: IP = Rev IP, "Taxes"
B18: a | C18: 1 | D18: C | E18: PO Sent to Vendor | F18: d | G18: 5 | H18: G | I18: inv/services received | T18: G | U18: Generic | V18: IP=State of VA
T19: E
T20: O
B22: Inventory - Finished Goods (Financial Account) | K22: Fund | T22: Entry | U22: Event Code
L23: File | M23: Arrg | N23: 3010001 | P23: File | Q23: Arrg | T23: a | U23: EV01-2017 | V23: PO Sent, and AP commitment recognized; Ledger=FIN
K24: i | L24: 7 | M24: G | N24: Year End Closeout | O24: i | P24: 7 | Q24: G | R24: Year End Closeout | T24: b
T25: c
B26: Asset Account (BUDGET) | K26: Expense Account (use Undefined Expense) | T26: d | U26: EV04-2017 | V26: Pay invoices for everything
C27: File | D27: Arrg | E27: 1090001 | G27: File | H27: Arrg | L27: File | M27: Arrg | N27: 4000000 | P27: File | Q27: Arrg | T27: e
B28: j | C28: 8 | D28: G | E28: Budget (Capital) Amounts | K28: j | L28: 8 | M28: G | N28: Budget (Operating) Amounts | T28: g
T29: h | U29: EV07 | V29: Tax Receipts (including sales of goods)
K30: Fund Account | T30: i | U30: EV08 | V30: Year-end
L31: File | M31: Arrg | N31: 3010003 | P31: File | Q31: Arrg | T31: J | U31: EV09 | V31: Load Budgets. If BUDGET_TYPE = OPERATING, Use Expense Account. Else if BUDGET_TYPE = CAPITAL, Use Asset Account. Else Error
O32: j | P32: 8 | Q32: G | R32: Budget Amounts

Sheet VA Journal Attributes (FPEM)
E2: Not Confirmed | F2: Not Confirmed | G2: Not Confirmed | H2: Not Confirmed
A3: FPEM Enteerd | B3: Field Contents | C3: Field Name | D3: FPEM Field Name | E3: Disk Field Format | F3: Memory Field Format | G3: Field Content | H3: Length | I3: Standard Values Used on Most Records | J3: 2017 Data | K3: Description | L3: Structure | M3: PO Example Field | N3: Payment Example Field
C4: Universal Journal | D4: Universal Journal | K4: Common on All Bus. Process
A5: Yes | B5: Source System ID | C5: ujSourceID | D5: src_cd | E5: String | F5: Text | G5: Constant | H5: 16 | I5: See specific values for different record types | K5: Identifier of system or system compoent that created the journal | L5: Universal Journal
A6: Yes | B6: Instrument/Contract ID | C6: ujInstrumentID | D6: arr_num | E6: String | F6: Long | G6: Xref Key | I6: See specific values for different record types | L6: Universal Journal
A7: Yes | B7: Legal Entity (CO. / Owner) | C7: ujLegalEntityID | D7: org_unit_cd | E7: String | F7: Int | G7: Xref Key | H7: 16 | I7: Agency key | J7: Agency key using reverse lookup | K7: Legal Entity, personal identifier | L7: Universal Journal | M7: AGENCY
A8: Yes | D8: partner_org_unit_cd | E8: String | F8: Long | G8: Xref Key | H8: 15 | I8: Blank, nothing in this data to put here. Same as Partner Org Code | L8: Universal Journal | M8: VENDORID
A9: Yes | B9: Center ID | C9: ujCenterID | D9: cost_center | E9: String | F9: Int | G9: Xref Key | H9: 16 | I9: Fund Key | J9: FUND_NAME | K9: Cost or Profit Center | L9: Universal Journal
A10: Yes | B10: Nominal Account | C10: ujAccountID | D10: acct_num | E10: String | F10: Int | G10: Xref Key | I10: COA value (through Object for payments, or Source for Rev. or ARE Rule specific values for POs) | J10: Object/Source Key using Reverse Lookup | K10: Category of the journal, chart of account value | L10: Universal Journal
A11: Yes | D11: event_id | E11: String | F11: Text | G11: Constant | H11: 16 | I11: Will generated unique Event ID | L11: Universal Journal
A12: Yes | B12: Business Event Code | C12: ujBusEventCD | D12: event_cd | E12: String | F12: Text | G12: Constant | H12: 16 | I12: See specific values for different record types | L12: Universal Journal
A13: Yes | B13: Currency Type Code Source | C13: ujCurrencyTypeCodeSourceID | D13: src_curr_type_cd | E13: String | F13: Text | G13: Constant | H13: 16 | I13: Per platform requirements | L13: Universal Journal
A14: Yes | B14: Curr. Code Source | C14: ujCurrencyCodeSourceID | D14: src_curr_cd | E14: String | F14: Text | G14: Constant | H14: 16 | I14: USD (for first test case) | L14: Universal Journal
A15: Yes | B15: Currency Type Code Target | C15: ujCurrencyTypeCodeTargetID | D15: tgt_curr_type_cd | E15: String | F15: Text | G15: Constant | H15: 16 | I15: Per platform requirements | L15: Universal Journal
A16: Yes | B16: Curr. Code Target | C16: ujCurrencyCodeTargetID | D16: tgt_curr_cd | E16: String | F16: Text | G16: Constant | H16: 16 | I16: USD (for first test case) | L16: Universal Journal
A17: Yes | B17: Acctg. Date | C17: ujAcctDate | D17: acct_dt | E17: String | F17: Date | G17: Derived | I17: First day of quarter per file containing data, or PO Date for PO Data | L17: Universal Journal
A18: Yes | B18: Transaction Amount | C18: ujTransAmount | D18: txn_amt | E18: BigDecimal | F18: Number | G18: Value | I18: Amount | L18: Universal Journal
A19: Yes | B19: Process Date | C19: ujProcessDate | D19: processing_date | E19: String | F19: Date | G19: Input Field | I19: ? | L19: Universal Journal | M19: ORDEREDDATE
A20: Yes | B20: Debit Credit Indicator | C20: ujDebitCreditFlg | D20: db_cr_ind | E20: String | F20: Boolean | G20: Constant | H20: 1 | I20: Filled in by Accounting Rules? | L20: Universal Journal | M20: UNITOFMEASURECODE
A21: Yes | B21: Jrnl Line No | C21: ujJrnlLineID | D21: jrnl_line_id | E21: String | F21: Int | G21: Unique ID | I21: Payment records (Pay and Rev) only result in one journal entry per row (so line number is unimportant). PO data when there are multiple rows per PO Number, should be a sequential number of the PO Row Number for a specific PO | L21: Universal Journal
A22: Yes | B22: Journal / Event Description | C22: ujJrnlDescript | D22: jrnl_line_desc | E22: String | F22: Text | G22: Input Field | H22: 2000 | I22: A simple text value of the source of this data | L22: Universal Journal
A23: Yes | B23: Business Function Code | D23: bus_func_cd | E23: String | F23: Text | G23: Constant | H23: 16 | I23: I think this field may actually be very similar to the Event Code. We might be able to delete this field | K23: Identifier of system or system compoent that created the journal | L23: Universal Journal
A24: Yes | B24: Book-code / Basis | C24: ujBookCodeID | D24: book_cd | E24: String | F24: Text | G24: Constant | H24: 16 | I24: USGAAP (for first test) | L24: Universal Journal
A25: Yes | B25: Involved Party ID | C25: ujIPID | D25: ip_rec_id | E25: String | F25: Long | G25: Xref Key | H25: 15 | I25: See specific values for different record types | L25: Universal Journal | M25: VENDORID
A26: Yes | B26: Commitment ID | C26: ujCommitmentID | D26: ujCommitmentID | E26: String | F26: Long | G26: Xref Key | I26: See specific values for different record types | L26: UJ PO Extension
A27: Yes | B27: Original Process ID | C27: ujProcessID | D27: ujProcessID | E27: String | F27: Text | G27: Constant | H27: 16 | I27: I think this field may actually be very similar to the Event Code. We might be able to delete this field | K27: Identifier of system or system compoent that created the journal | L27: Universal Journal
A28: Yes | B28: Original Document ID | C28: ujOriginalDocID | D28: ujOriginalDocID | E28: String | F28: Text | H28: 50 | I28: PO Number on PO records. The row number of the record + File name, to be able to trace to original input record | L28: Universal Journal | M28: PONUMBER
A29: Yes | B29: Ledger | C29: ujLedgerID | D29: ujLedgerID | E29: String | F29: Text | G29: Constant | H29: 16 | I29: "FIN" for Payment Data (Pay and Rev) "CMT" for Commitment books, for PO data | L29: Universal Journal
A30: Yes | B30: Jrnl Type | C30: ujJrnlType | D30: ujJrnlType | E30: String | F30: Text | G30: Constant | H30: 16 | I30: "ACT" for all these records An Actual Financial Journal | K30: ANA - Analytical Journal, such as an allocation process STS - A Statistical Journal, containing a non-monetary value FRC - A Forecast Journal RCN - Reconciliation Balance used to agree to another ledger ACT - An Actual Financial Journal | L30: Universal Journal
A31: Yes | B31: Affiliate Owner ID | C31: ujAffliateEntityID | D31: ujAffliateEntityID | E31: String | F31: Int | G31: Xref Key | H31: 16 | I31: Blank, nothing in this data to put here. Same as Partner Org Code | K31: Counterparty to transaction | L31: Universal Journal
A32: Yes | B32: Project ID | C32: ujProjectID | D32: ujProjectID | E32: String | F32: Int | G32: Xref Key | H32: 16 | I32: Value from Program field on Payment (Pay and Rev) Data | J32: PROGRAM_NAME | L32: Universal Journal
A33: Yes | B33: Product / Material ID | C33: ujProductID | D33: ujProductID | E33: String | F33: Int | G33: Constant | I33: NIGP Code for PO Data. Blank for Puchase and Rev Data | L33: Universal Journal
A34: Yes | B34: Alternate Account Code | C34: ujAltAccountID | D34: ujAltAccountID | E34: String | F34: Int | G34: Constant | I34: Blank, nothing in this data to put here | L34: Universal Journal
A35: Yes | B35: Fiscal Period | C35: ujFiscalPeriod | D35: ujFiscalPeriod | E35: String | F35: Date | G35: Derived | I35: Let's make this the year of the record. It would typically be a month, but because we only get revenue data yearly, let's just say year on all records | L35: Universal Journal
A36: Yes | B36: Transaction Date | C36: ujTransDate | D36: ujTransDate | E36: String | F36: Date | G36: Input Field | I36: Same as acocunting data for all input records | L36: Universal Journal | M36: ORDEREDDATE
A37: Yes | B37: Movement Flag | C37: ujMovementFlg | D37: ujMovementFlg | E37: String | F37: Boolean | G37: Constant | H37: 1 | I37: Do we use movements on the platform? If we do, we can put a Y here. If not, then a N | K37: Indicates if amount is a movement. If not, it is an accumulation | L37: Universal Journal
A38: Yes | B38: Direct vs. Offset Flag | C38: ujDirVsOffsetFlg | D38: ujDirVsOffsetFlg | E38: String | F38: Boolean | G38: Constant | H38: 1 | I38: For all input records it should be a Y. For all records generated by Accounting Rules (offsets to other accounts) it should be a N | L38: Universal Journal
A39: Yes | B39: Reconciliable Flag | C39: ujReconcileFlg | D39: ujReconcileFlg | E39: String | F39: Boolean | G39: Constant | H39: 1 | I39: N for all this data as we have no balances to test these things against | K39: Indicates if associated balance can be reconciled elsewhere | L39: Universal Journal
A40: Yes | B40: Adjustment Flag | C40: ujAdjustFlg | D40: ujAdjustFlg | E40: String | F40: Boolean | G40: Constant | H40: 1 | I40: N for all input data. Only entries that someone makes by hand and loads to the system should be Y | K40: Indicates if journal is an adjustment as opposed to a automated feed | L40: Universal Journal
A41: Yes | B41: Statistical Amount/Quantity | C41: ujStatisticalAmount | D41: ujStatisticalAmount | E41: BigDecimal | F41: Number | G41: Value | I41: Qunaity for any inventory record. Otherwise blank | L41: Universal Journal | M41: QUANTITYORDERED
A42: Yes | B42: Rule Set ID | C42: ujRuleSetID | D42: ujRuleSetID | E42: String | F42: Text | G42: Constant | H42: 16 | L42: Universal Journal
A43: Yes | B43: Rule ID | C43: ujRuleID | D43: ujRuleID | E43: String | F43: Text | G43: Constant | H43: 16 | L43: Universal Journal
A44: Yes | B44: Audit Trial Extension ID | C44: ujExtensionIDAuditTrail | D44: ujExtensionIDAuditTrail | E44: String | F44: int | G44: Xref Key | I44: We can probably delete these fields as your system maintains connectivity to the audit trail records | L44: Universal Journal
A45: Yes | B45: Source Extension ID | C45: ujExtensionIDSource | D45: ujExtensionIDSource | E45: String | F45: int | G45: Xref Key | I45: We can probably delete these fields as your system maintains connectivity to the audit trail records | L45: Universal Journal
A46: Yes | B46: Classification Extension ID | C46: ujExtensionIDClass | D46: ujExtensionIDClass | E46: String | F46: int | G46: Xref Key | I46: We can probably delete these fields as your system maintains connectivity to the audit trail records | L46: Universal Journal
A47: Yes | B47: Date Extension ID | C47: ujExtensionIDDates | D47: ujExtensionIDDates | E47: String | F47: int | G47: Xref Key | I47: We can probably delete these fields as your system maintains connectivity to the audit trail records | L47: Universal Journal
A48: Yes | B48: Other Customization Ext ID | C48: ujExtensionIDCustom | D48: ujExtensionIDCustom | E48: String | F48: int | G48: Xref Key | I48: We can probably delete these fields as your system maintains connectivity to the audit trail records | L48: Universal Journal
A49: Yes | B49: Unit of Measure | C49: ujUnitOfMeasure | D49: ujUnitOfMeasure | E49: String | F49: Text | G49: Constant | H49: 50 | I49: Unit of Measure for any Inventory record. Otherwise blank | L49: Universal Journal | M49: UNITOFMEASURECODE
A50: Yes | B50: Uniit Price | C50: ujUnitPrice | D50: ujUnitPrice | E50: BigDecimal | F50: Number | G50: Value | I50: Price per unit for any inventory record. Otherwise blank | J50: Expense Records | K50: Revenue Records | L50: Universal Journal | M50: PRICE
B51: Can we add these new fields on to the end of the record, for 2017 data? | C51: BRANCH_NAME | J51: BRANCH_NAME | K51: BRANCH_NAME
C52: SECRETARIAT_NAME | J52: SECRETARIAT_NAME | K52: SECRETARIAT_NAME
C53: AGENCY_NAME
C54: FUNCTION_NAME | J54: FUNCTION_NAME
C55: PROGRAM_NAME
C56: SERVICE_AREA_NAME | J56: SERVICE_AREA_NAME
C57: FUND_NAME
C58: FUND_DETAIL_NAME | J58: FUND_DETAIL_NAME | K58: FUND_DETAIL_NAME
C59: CATEGORY_NAME | J59: CATEGORY_NAME | K59: CATEGORY_NAME
C60: EXPENSE-SOURCE_TYPE
A61: Not on SJE | B61: Extended Amount | C61: ujExtendedAmount | D61: ujExtendedAmount | E61: BigDecimal | F61: Number | G61: Value
A62: Not on SJE | B62: Spot Exchange Rate | C62: ujSpotExchangeRate | D62: ujSpotExchangeRate | E62: BigDecimal | F62: Number | G62: Value | L62: Universal Journal
A63: Not on SJE | B63: Instrument/Contract ID SubArrangement | C63: ujInstrumentID | D63: ujInstrumentID | E63: String | F63: Long | G63: Xref Key | L63: Universal Journal
A64: Not on SJE | B64: Business Event / Journal ID | C64: ujJrnlID | D64: ujJrnlID | E64: String | F64: Long | G64: Unique ID | K64: Unique identifier for each business event/universal journal | L64: Universal Journal
A65: Not on SJE | B65: Affliate Center ID | C65: ujAffliateCenterID | D65: ujAffliateCenterID | E65: String | F65: Int | G65: Xref Key | H65: 16 | L65: Universal Journal
C66: Instrument/Contract | D66: Instrument/Contract | K66: Unique by Business Process
A67: Yes | B67: Source System ID | C67: ujSourceID | D67: src_cd | E67: String | F67: Text | G67: Constant | H67: 16 | I67: Same as Event Journal | K67: Identifier of system or system compoent that created the journal | L67: Universal Journal
A68: Yes | B68: Instrument/Contract ID | C68: ujInstrumentID | D68: arr_num | E68: String | F68: Long | G68: Xref Key | I68: Same as Event Journal | L68: Universal Journal
A69: Yes | B69: Legal Entity (CO. / Owner) | C69: ujLegalEntityID | D69: org_unit_cd | E69: String | F69: Int | G69: Xref Key | H69: 16 | I69: Same as Event Journal | K69: Legal Entity, personal identifier | L69: Universal Journal | M69: AGENCY
A70: Yes | D70: event_id | E70: String | F70: Text | G70: Constant | H70: 16 | I70: Same as Event Journal | L70: Universal Journal
A71: Yes | B71: Business Event Code | C71: ujBusEventCD | D71: event_cd | E71: String | F71: Text | G71: Constant | H71: 16 | I71: Same as Event Journal | L71: Universal Journal
A72: Yes | B72: Acctg. Date | C72: ujAcctDate | D72: acct_dt | E72: String | F72: Date | G72: Derived | I72: Same as Event Journal | L72: Universal Journal
A73: Yes | B73: Process Date | C73: ujProcessDate | D73: processing_date | E73: String | F73: Date | G73: Input Field | I73: Same as Event Journal | L73: Universal Journal | M73: ORDEREDDATE
A74: Yes | B74: Involved Party ID | C74: uiIPID | D74: uiIPID | E74: String | F74: Long | G74: Xref Key | I74: Same as Event Journal | L74: Universal Contract | M74: VENDORID
A75: Yes | B75: Entry Date | D75: entryDate | E75: String | F75: Date | G75: Blank | L75: Universal Contract | M75: ORDEREDDATE
A76: Yes | B76: Update Date | D76: updateDate | E76: String | F76: Date | G76: Blank | L76: Universal Contract | M76: ORDEREDDATE
A77: Yes | B77: Approver ID | D77: approverID | E77: String | F77: Text | G77: Value | L77: Universal Contract
A78: Yes | B78: Creator ID | D78: creatorID | E78: String | F78: Text | G78: Value | L78: Universal Contract
A79: Yes | B79: Entry Hash of Credits | D79: creditHashTotal | E79: String | F79: Text | G79: Value | L79: Universal Contract
A80: Yes | B80: Entry Hash of Debits | D80: deditHashTotal | E80: String | F80: Text | G80: Value | L80: Universal Contract
A81: Yes | B81: Contract Type | C81: uiInstrumentType | D81: uiInstrumentType | E81: String | F81: Text | G81: Value | L81: Universal Contract
A82: To Be Added | B82: Invenotry or Service Type | C82: uilInventoryType | E82: string | F82: text | I82: NIGP < 900 = "Inventory" NIGP > 900 = "Service"
A83: Yes | B83: NIGP Code | C83: ujepoNIGPcode | D83: ujepoNIGPcode | E83: String | F83: Text | H83: 12 | L83: UJ PO Extension | M83: NIGPCODE
A84: Yes | B84: NIGP Class Code Description | C84: ujepoNIGPDescription | D84: ujepoNIGPDescription | E84: String | F84: Text | H84: 500 | L84: UJ PO Extension | M84: NIGPDESCRIPTION
A85: To Be Added | B85: SAL Type | C85: uilSALType | E85: string | F85: text | I85: "PO With Payment" or "Payment With PO" or "Payment W/O PO" or "Inventory" or "PO W/O Payment" or "PO All" or "Payment All" or "Taxes" or "Other"
C87: Invovled Party | D87: Invovled Party | I87: All of the below should be pretty clear how to populate them from PO data or from the new Revenue IP table. Unique Vendors which do not have PO Vendor data will only have the IP Name assigned for them.
A88: Yes | B88: Source System ID | C88: ujSourceID | D88: src_cd | E88: String | F88: Text | G88: Constant | H88: 16 | K88: Identifier of system or system compoent that created the journal | L88: Universal Journal
A89: Yes | B89: Instrument/Contract ID | C89: ujInstrumentID | D89: arr_num | E89: String | F89: Long | G89: Xref Key | L89: Universal Journal
A90: Yes | B90: Legal Entity (CO. / Owner) | C90: ujLegalEntityID | D90: org_unit_cd | E90: String | F90: Int | G90: Xref Key | H90: 16 | K90: Legal Entity, personal identifier | L90: Universal Journal | M90: AGENCY
A91: Yes | D91: event_id | E91: String | F91: Text | G91: Constant | H91: 16 | L91: Universal Journal
A92: Yes | B92: Business Event Code | C92: ujBusEventCD | D92: event_cd | E92: String | F92: Text | G92: Constant | H92: 16 | L92: Universal Journal
A93: Yes | B93: Acctg. Date | C93: ujAcctDate | D93: acct_dt | E93: String | F93: Date | G93: Derived | L93: Universal Journal
A94: Yes | B94: Process Date | C94: ujProcessDate | D94: processing_date | E94: String | F94: Date | G94: Input Field | L94: Universal Journal | M94: ORDEREDDATE
A95: Yes | B95: Involved Party ID | C95: uiIPID | D95: uiIPID | E95: String | F95: Long | G95: Xref Key | L95: Universal Contract | M95: VENDORID
A96: Yes | D96: event_id | E96: String | F96: Text | G96: Constant | H96: 16 | L96: Universal Journal
A97: Yes | B97: Business Event Code | C97: ujBusEventCD | D97: event_cd | E97: String | F97: Text | G97: Constant | H97: 16 | L97: Universal Journal
A98: Yes | B98: IP Name | C98: ipName | D98: ipName | E98: String | F98: Text | G98: Value | H98: 128 | L98: Involved Party | M98: VENDORNAME
A99: Yes | B99: IP Address | C99: ipAddress | D99: ipAddress | E99: String | F99: Text | G99: Value | H99: 255 | L99: Involved Party | M99: VENDORADDRESS
A100: Yes | B100: IP City | C100: ipCity | D100: ipCity | E100: String | F100: Text | G100: Value | H100: 255 | L100: Involved Party | M100: VENDORCITY
A101: Yes | B101: IP State | C101: ipState | D101: ipState | E101: String | F101: Text | G101: Value | H101: 50 | L101: Involved Party | M101: VENDORSTATE
A102: Yes | B102: IP Country | C102: ipCountry | D102: ipCountry | E102: String | F102: Text | G102: Constant | H102: 255 | L102: Involved Party
...

Sheet CofA
H4: DOCUMENTATION ONLY
B5: LEVEL 5 | C5: COA_NOMIINAL_ACCOUNT | D5: COA_ACCOUNT_TYPE | E5: COA_CLASS_CODE | F5: COA_ACCOUNT_NAME | H5: COA_LEDGER_TYPE
C6: 1010001 | D6: 1 | E6: 110 | F6: CASH | H6: FIN
C7: 1010101 | D7: 1 | E7: 110 | F7: ACCOUNTS RECEIVABLE | H7: FIN
C8: 1020001 | D8: 1 | E8: 120 | F8: INVENTORY – WORK IN PROGRESS | H8: FIN
C9: 1020011 | D9: 1 | E9: 120 | F9: INVENTORY – FINISHED GOODS | H9: FIN
C10: 1020101 | D10: 1 | E10: 120 | F10: INVENTORY RECEIVABLE | H10: CMT
C11: 1030001 | D11: 1 | E11: 130 | F11: PREPAYMENTS | H11: FIN
C12: 1030101 | D12: 1 | E12: 130 | F12: EQUIPMENT – LAB | H12: FIN
C13: 1030201 | D13: 1 | E13: 130 | F13: ACCUMULATED DEPRECIATION – LAB EQUIPMENT | H13: FIN
C14: 1030301 | D14: 1 | E14: 130 | F14: EQUIPMENT – OFFICE | H14: FIN
C15: 1030401 | D15: 1 | E15: 130 | F15: ACCUMULATED DEPRECIATION – OFFICE EQUIPMENT | H15: FIN
C16: 1030501 | D16: 1 | E16: 130 | F16: LEASEHOLD IMPROVEMENTS | H16: FIN
C17: 1030601 | D17: 1 | E17: 130 | F17: ACCUMULATED AMORTIZATION – LEASEHOLD IMPROVEMENTS | H17: FIN
... C27: 3010003 | D27: 3 | E27: 310 | F27: FUND BUDGET | H27: BUDGET-CAPITAL
C28: 4000000 | D28: 4 | E28: 400 | F28: UNDEFINED | H28: FIN, AND BUDGET-OPERATNG
C29: 4001000 | D29: 4 | E29: 401 | F29: TAXES | H29: FIN
C30: 4001001 | D30: 4 | E30: 401 | F30: RAILROAD COMPANIES | H30: FIN
C31: 4001002 | D31: 4 | E31: 401 | F31: RETAIL SALES TIRE TAX | H31: FIN
C32: 4001003 | D32: 4 | E32: 401 | F32: CAR LINE COMPANIES | H32: FIN
C33: 4001005 | D33: 4 | E33: 401 | F33: COMMUNICATIONS SALES AND USE TAX - VA RELAY | H33: FIN
C34: 4001006 | D34: 4 | E34: 401 | F34: LIGHT,HEAT,POWER & WATER COMPANIES | H34: FIN
C35: 4001007 | D35: 4 | E35: 401 | F35: ELECTRIC CONSUMPTION TAX | H35: FIN
C36: 4001008 | D36: 4 | E36: 401 | F36: NATURAL GAS CONSUMPTION TAX | H36: FIN
C37: 4001009 | D37: 4 | E37: 401 | F37: SCC-RAILROAD SPECIAL TAX | H37: FIN
C38: 4001010 | D38: 4 | E38: 401 | F38: VALUATION TAXES ON CERTAIN PUBLIC SERVICE CORP | H38: FIN
C39: 4001011 | D39: 4 | E39: 401 | F39: MOTOR VEHICLE CARRIERS-ROLLING STOCK TAX | H39: FIN
C40: 4001012 | D40: 4 | E40: 401 | F40: COMMUNICATIONS SALES AND USE TAX | H40: FIN
... C2774: 5087LF0 | D2774: 5 | E2774: 587 | F2774: INDIRECT COSTS - LOCAL FUNDS | H2774: FIN
C2775: 6000001 | D2775: 6 | E2775: 610 | F2775: TRANSFERS | H2775: FIN
C2776: 7000000 | D2776: 7 | E2776: 700 | F2776: SUSPENSE | H2776: FIN

Sheet Other Tables
A2: Level 3 | B2: COA_ACCOUNT_TYPE | C2: COA_ACCOUNT_TYPE_DESCRIPTION | E2: ARRANGEMENT_TYPE_CODE | F2: ARRANGEMENT_TYPE_DESCRIPTION
B3: 1 | C3: ASSET | E3: 1 | F3: ASSET
B4: 2 | C4: LIABILITY | E4: 2 | F4: LIABILITY
B5: 3 | C5: FUND BALANCE (EQUITY) | E5: 3 | F5: FUND BALANCE (EQUITY)
B6: 4 | C6: REVENUE | E6: 4 | F6: REVENUE
B7: 5 | C7: EXPENSE | E7: 5 | F7: EXPENSE
B8: 6 | C8: TRANSFER | E8: 6 | F8: TRANSFER
B9: 7 | C9: SUSPENSE | E9: 7 | F9: SUSPENSE
E11: hold on this table….
A12: Level 4 | B12: COA_CLASS_CODE | C12: COA_CLASS_DESCRIPTION | E12: COMMITMENT_TYPE_CODE | F12: COMMITMENT_TYPE_DESCRIPTION
B13: 110 | C13: CURRENT ASSETS | E13: 0 | F13: NO COMMITMENT
B14: 120 | C14: INVENTORY | E14: 110 | F14: PAYMENT WITHOUT PO
B15: 130 | C15: PROPERTY, PLANT & EQUIPMENT | E15: 120 | F15: PO WITHOUT PAYMENT
B16: 140 | C16: OTHER ASSETS | E16: 130 | F16: PAYMENT WITH PO
B17: 190 | C17: BUDGET | E17: 140 | F17: PO WITH PAYMENT
B18: 210 | C18: CURRENT LIABILITIES
B19: 220 | C19: LONG TERM LIABILITIES | E19: LEDGER ID VALUES
B20: 310 | C20: FUND BALANCE | E20: FIN | F20: FINANCIAL ACCOUNTING BOOKS
B21: 400 | C21: UNDEFINED | E21: CMT | F21: COMMITMENT/EXPOSURE BOOKS
B22: 401 | C22: TAXES | E22: BUDGET-OPERATING | F22: BUDGET OPERATING
B23: 402 | C23: RIGHTS AND PRIVILEGES | E23: BUDGET-CAPITAL | F23: BUDGET CAPITAL
B24: 403 | C24: SALES OF PROPERTY AND COMMODITIES
B25: 404 | C25: DONATIONS, RECEIPTS AND TRANSFERS | D25: Level 2 | E25: STATEMENT_TYPE
B26: 405 | C26: ASSESSMENTS AND RECEIPTS FOR SUPPORT FOR SPECIAL SERVICES | E26: 1 | F26: BALANCE SHEET
B27: 406 | C27: INSTITUTIONAL REVENUE | E27: 2 | F27: INCOME STATEMENT
B28: 407 | C28: INTEREST, DIVIDEND AND RENTS
B29: 408 | C29: FINES, FORFEITURES, COURT FEES, CODES, PENALTIES, AND ESCHEATS
B30: 409 | C30: OTHER REVENUE | D30: Level 1 | E30: 1 | F30: TRIAL BALANCE
B31: 410 | C31: FEDERAL GRANTS AND CONTRACTS
B32: 411 | C32: FEDERAL GRANTS AND CONTRACTS
B33: 412 | C33: FEDERAL GRANTS AND CONTRACTS
B34: 414 | C34: FEDERAL GRANTS AND CONTRACTS
B35: 415 | C35: FEDERAL GRANTS AND CONTRACTS
B36: 416 | C36: FEDERAL GRANTS AND CONTRACTS
B37: 417 | C37: FEDERAL GRANTS AND CONTRACTS
B38: 419 | C38: FEDERAL GRANTS AND CONTRACTS
B39: 420 | C39: FEDERAL GRANTS AND CONTRACTS
B40: 421 | C40: FEDERAL GRANTS AND CONTRACTS
B41: 423 | C41: FEDERAL GRANTS AND CONTRACTS
B42: 427 | C42: FEDERAL GRANTS AND CONTRACTS
... B94: 591 | C94: SUBGRANTS TO STATE AGENCIES
B95: 610 | C95: TRANSFERS
B96: 700 | C96: SUSPENSE

Sheet CoA Structure
B2: The following is a reconstruction of the VA Chart of Account, based upon documents: https://www.doa.virginia.gov/reference/CAPP/CAPP_Topics_Cardinal/60101.pdf), https://www.doa.virginia.gov/reference/CAPP/CAPP_Topics_Cardinal/60106.pdf
B5: Cardinal Account ChartField | C5: Account Type
B6: 1XXXXXX | C6: Asset
B7: 2XXXXXX | C7: Liability
B8: 3XXXXXX | C8: Fund Balance (Equity)
B10: 4XXXXXX | C10: Revenue (Operating)
B11: 5XXXXXX | C11: Expenditure (Operating)
B12: 6XXXXXX | C12: Transfer (Operating)
B13: 7 | C13: Suspense
B15: Revenue Accounts are constructed by using the SOURCE Table
C16: 40 + XXXXX (Source Field Value)
C18: the XXXXX can be broken down into:
C19: XX = Class
C20: X = Sub Class
C21: XX = Detailed Source
B23: Expense Accounts are constructued by using the OBJECT Table
C24: 50 + XXXX + 0

Sheet 2019 Rev Source XREF
A1: 2017_SRC_SOURCE_NAME | B1: ADJ_2003_SRC_SOURCE_NAME | C1: SRC_SOURCE_KEY
A2: 1890 Institutn Capcty Bldg Grt | B2: 1890 INSTITUTION CAPACITY BLDG GRANTS | C2: 1439
A3: 2% Motor Fuel Tax | B3: 2% MOTOR FUEL TAX | C3: 9446
A4: 21St Century Comm Learning Ctr | B4: 2% MOTOR FUEL TAX | C4: 9446
A5: 2nd Chce Act Prsnr Rentry Intv | B5: 2% MOTOR FUEL TAX | C5: 9446
A6: Aband Mine Land Reclamatn Pgm | B6: A CERTIFICATE OF LIMITED PARTNERSHIP | C6: 966
A7: ABC Licenses Application Fees | B7: ABC LICENSES APPLICATION FEES | C7: 522
A8: ABC Liter Tax-Localities Share | B8: ABC LITER TAX-LOCALITIES SHARE | C8: 293
A9: ABC Profits | B9: ABC PROFITS | C9: 794
A10: ABC State Sales And Use Tax | B10: ABC STATE SALES AND USE TAX | C10: 478
A11: ABLEnow-Admin Fee | B11: ABC STATE SALES AND USE TAX | C11: 478
A12: Abstinence Education | B12: ABSTINENCE EDUCATION | C12: 531
A13: ACA Hlth Profess Opport Grants | B13: Aca Hlth Profess Opport Grants | C13: 9575
... A1363: Yorktwn Victry Ctr Adm Receipt | B1363: YORKTOWN VICTORY CENTER ADMISSION RECEIPTS | C1363: 882

Sheet 2019 Exp Object XREF
A1: 2017_EXPENSE_TYPES | B1: ADJ_2003_4-DIGIT OBJECT NAME | C1: OBJ_OBJECT_KEY
A2: Acquisition, Bridges | B2: ACQUISITION, BRIDGES | C2: 197
A3: Acquisition, Buildings | B3: ACQUISITION, BUILDINGS | C3: 198
A4: Acquisition, Property | B4: ACQUISITION, PROPERTY | C4: 439
A5: Acquisition, Rights-Of-Way | B5: ACQUISITION, RIGHTS-OF-WAY | C5: 440
A6: Acquisition, Watrway&Imprvemnt | B6: ACQUISITION, WATERWAYS & IMPROVEMENTS | C6: 441
A7: Admin Costs/Local Programs | B7: ADMINISTRATIVE COSTS/LOCAL PROGRAMS | C7: 221
A8: Administrative Costs | B8: ADMINISTRATIVE COSTS | C8: 426
A9: Agency Indirect Cost Recovery | B9: AGENCY INDIRECT COST RECOVERIES | C9: 236
A10: Agency Service Charges | B10: AGENCY SERVICE CHARGES | C10: 377
A11: Agricultural Supplies | B11: AGRICULTURAL SUPPLIES | C11: 335
A12: Agricultural Vehicular Equip | B12: AGRICULTURAL VEHICULAR EQUIPMENT | C12: 108
A13: Aircraft Equipment | B13: AIRCRAFT EQUIPMENT | C13: 109
... A371: X-Ray & Laboratory Services | B371: X-RAY & LABORATORY SERVICES | C371: 140

Sheet Revenue IPs
A3: CATEGROY | B3: IP Name | C3: IP Address | D3: IP City | E3: IP State | F3: IP Country | G3: IP Postal Code | H3: IP e-mail | I3: IP Vendor ID | J3: IP Unit ID: | K3: IP District ID: | L3: IP Source System ID | P3: 2017 Data
A4: 00 | B4: UNDEFINED | C4: UNKNOWN | D4: UNKNOWN | E4: UNKNOWN | I4: 00 | J4: UNDEFINED | P4: ASSESSMENTS AND RECEIPTS FOR SUPPORT OF SPECIAL SERVICES
A5: 01 | B5: TAXPAYERS | C5: UNKNOWN | D5: UNKNOWN | E5: VA | I5: 01 | J5: TAXES | P5: DONATIONS, RECEIPTS, AND TRANSFERS
A6: 02 | B6: TAXPAYERS FOR RIGHT AND PRIVILEGES | C6: UNKNOWN | D6: UNKNOWN | E6: VA | I6: 02 | J6: RIGHTS AND PRIVILEGES | P6: FEDERAL GRANTS AND CONTRACTS
A7: 03 | B7: VARIOUS BUYERS | C7: UNKNOWN | D7: UNKNOWN | E7: VA | I7: 03 | J7: SALES OF PROPERTY AND COMMODITIES | P7: FINES, FORFEITURES, COURT FEES, COSTS, PENALTIES, AND ESCHEATS
A8: 04 | B8: CONTRIBUTORS | C8: UNKNOWN | D8: UNKNOWN | E8: UNKNOWN | I8: 04 | J8: DONATIONS, RECEIPTS AND TRANSFERS | P8: INSTITUTIONAL REVENUE
A9: 05 | B9: ASSESSORS | C9: UNKNOWN | D9: UNKNOWN | E9: UNKNOWN | I9: 05 | J9: ASSESSMENTS AND RECEIPTS FOR SUPPORT FOR SPECIAL SERVICES | P9: INTEREST, DIVIDENDS, AND RENTS
A10: 06 | B10: INSTITUTIONS | C10: UNKNOWN | D10: UNKNOWN | E10: UNKNOWN | I10: 06 | J10: INSTITUTIONAL REVENUE | P10: OTHER REVENUE
A11: 07 | B11: FINANCIAL SERVICES PARTNER | C11: UNKNOWN | D11: UNKNOWN | E11: UNKNOWN | I11: 07 | J11: INTEREST, DIVIDEND AND RENTS | P11: RIGHTS AND PRIVILEGES
A12: 08 | B12: LITIGANTS | C12: UNKNOWN | D12: UNKNOWN | E12: UNKNOWN | I12: 08 | J12: FINES, FORFEITURES, COURT FEES, CODES, PENALTIES, AND ESCHEATS | P12: SALES OF PROPERTY AND COMMODITIES
A13: 09 | B13: OTHERS REVENUE PARTIES | C13: UNKNOWN | D13: UNKNOWN | E13: UNKNOWN | I13: 09 | J13: OTHER REVENUE | P13: TAXES
A14: 10 | B14: FEDERAL GOVERNMENT | C14: UNKNOWN | D14: WASHINGTON DC | E14: DC | F14: US | I14: 10 | J14: FEDERAL GRANTS AND CONTRACTS | P14: TRANSFER PAYMENTS
A15: 11 | B15: FEDERAL GOVERNMENT | C15: UNKNOWN | D15: WASHINGTON DC | E15: DC | F15: US | I15: 11 | J15: FEDERAL GRANTS AND CONTRACTS
A16: 12 | B16: FEDERAL GOVERNMENT | C16: UNKNOWN | D16: WASHINGTON DC | E16: DC | F16: US | I16: 12 | J16: FEDERAL GRANTS AND CONTRACTS
A17: 14 | B17: FEDERAL GOVERNMENT | C17: UNKNOWN | D17: WASHINGTON DC | E17: DC | F17: US | I17: 14 | J17: FEDERAL GRANTS AND CONTRACTS
A18: 15 | B18: FEDERAL GOVERNMENT | C18: UNKNOWN | D18: WASHINGTON DC | E18: DC | F18: US | I18: 15 | J18: FEDERAL GRANTS AND CONTRACTS
A19: 16 | B19: FEDERAL GOVERNMENT | C19: UNKNOWN | D19: WASHINGTON DC | E19: DC | F19: US | I19: 16 | J19: FEDERAL GRANTS AND CONTRACTS
A20: 17 | B20: FEDERAL GOVERNMENT | C20: UNKNOWN | D20: WASHINGTON DC | E20: DC | F20: US | I20: 17 | J20: FEDERAL GRANTS AND CONTRACTS
A21: 19 | B21: FEDERAL GOVERNMENT | C21: UNKNOWN | D21: WASHINGTON DC | E21: DC | F21: US | I21: 19 | J21: FEDERAL GRANTS AND CONTRACTS
A22: 20 | B22: FEDERAL GOVERNMENT | C22: UNKNOWN | D22: WASHINGTON DC | E22: DC | F22: US | I22: 20 | J22: FEDERAL GRANTS AND CONTRACTS
A23: 21 | B23: FEDERAL GOVERNMENT | C23: UNKNOWN | D23: WASHINGTON DC | E23: DC | F23: US | I23: 21 | J23: FEDERAL GRANTS AND CONTRACTS
A24: 23 | B24: FEDERAL GOVERNMENT | C24: UNKNOWN | D24: WASHINGTON DC | E24: DC | F24: US | I24: 23 | J24: FEDERAL GRANTS AND CONTRACTS
A25: 27 | B25: FEDERAL GOVERNMENT | C25: UNKNOWN | D25: WASHINGTON DC | E25: DC | F25: US | I25: 27 | J25: FEDERAL GRANTS AND CONTRACTS
A26: 30 | B26: FEDERAL GOVERNMENT | C26: UNKNOWN | D26: WASHINGTON DC | E26: DC | F26: US | I26: 30 | J26: FEDERAL GRANTS AND CONTRACTS
... A53: 99 | B53: FEDERAL GOVERNMENT | C53: UNKNOWN | D53: WASHINGTON DC | E53: DC | F53: US | I53: 99 | J53: FEDERAL GRANTS AND CONTRACTS

Sheet New NIGP
B2: NIGP Code
B3: Class Description
B4: 500 | C4: Abrasives
B5: 505 | C5: Abrasive Equipment And Tools
B6: 514 | C6: Abrasives, Coated: Cloth, Fiber, Sandpaper, Etc.
B7: 521 | C7: Abrasives, Sandblasting, Metal
B8: 528 | C8: Abrasives, Sandblasting (Other Than Metal)
B9: 542 | C9: Abrasives, Solid: Wheels, Stones, Etc.
B10: 556 | C10: Abrasives, Tumbling (Wheel)
B11: 563 | C11: Grinding And Polishing Compounds: Carborundum, Diamond, Etc. (For Valve
B12: 570 | C12: Pumice Stone
B13: 575 | C13: Recycled Abrasives Products And Supplies
B14: 584 | C14: Steel Wool, Aluminum Wool, Copper Wool, And Lead Wool
B15: 1000 | C15: Acoustical Tile, Insulating Materials, And Supplies
... B747: 91086 | C747: Siding Installation And Repair Services
B974: 91200 CONSTRUCTION SERVICES, GENERAL (INCL. MAINTENANCE AND REPAIR
B975: SERVICES)
B976: NIGP
B977: Code
B978: Description
B979: 91200 CONSTRUCTION SERVICES, GENERAL (INCL. MAINTENANCE AND
B980: REPAIR SERVICES)
B981: 91216 Boring, Drilling, Testing, and Soundings
B982: 91219 Clearing and Grubbing Services
B983: 91220 Construction, Fire Protection (Includes Fire Escapes)
B984: 91221 Construction, Energy Related (All Types)
B985: 91222 Construction, Equestrian Arena
... B1157: 91584 Video Recording
B1158: 91585
B1159: Telecommunication Relay Services (Text Telephone (TTY); Text-To-Voice;
B1160: Voice Carry Over (VCO); Hearing Carry Over (HCO); Speech-To-Speech
B1161: Relay; Video Relay; Spanish Relay; 7-1-1 Access to TRS
B1162: 91590 Video Media Duplicating and Production Services (Including CD ROMs,
B1163: Tapes, etc.)
B1164: 91593 Voice Mail Services
B1165: 91595 Warning System Services, Citizen
B1166: 91596 Web Page Design, Management and Maintenance Services
B1167: 91597 Wiring Services, Data/Voice
B1168: 91800 CONSULTING SERVICES
B1169: NIGP
B1170: Code
... B1467: Description
B1468: 92800
B1469: EQUIPMENT MAINTENANCE AND REPAIR SERVICES FOR
B1470: AUTOMOBILES, TRUCKS, TRAILERS, TRANSIT BUSES AND OTHER
B1471: VEHICLES
B1472: 92804 Accessories (Not Otherwise Classified) Maintenance and Repair
B1473: 92810 Alignment and Wheel Balancing (Including Front-End Repair)
B1474: 92812 Ambulance and Rescue Vehicles Maintenance and Repair Services (Incl.
B1475: Major Components and Accessory Items)
B1476: 92815 Automobile and Other Passenger Vehicles Maintenance and Repair (Not
B1477: Otherwise Classified)
B1478: 92819 Body and Frame Work (Including Undercoating)
B1479: 92823 Brake Maintenance and Repair
B1480: 92824 Buses, School and Mass Transit, Maintenance and Repair
... B1498: General Maintenance and Repair, Vehicle (Not Otherwise Classified), to
B1499: 92847
B1500: General Maintenance and Repair, Vehicle (Not Otherwise Classified), to
B1501: Include Oil Changes, Lubrication, Guaranteed Maintenance Programs, etc.
B1502: (See 928-88 for Tune-Ups)
B1503: 92849 Hydraulics (Pump, Hydraulic Motor, Valves, Gauges, etc.) Maintenance and
B1504: Repair
B1505: 92851 License Identification System (Vehicle), Maintenance and Repair
B1506: 92854 Machine Shop Services, Automotive Type (See 929-48 for Industrial Type)
B1507: 92855 Motor Homes and Recreational Vehicles Maintenance and Repair
B1508: 92856 Oil Collection Services, Waste
B1509: 92857 Painting, Vehicle
B1510: 92858 Parts Washing Services
B1511: 92860 Power Plant (Engine, Belts, Heads, Intake, Rebuilding, etc.) Maintenance
... B1530: 92895 Welding Services, Automotive Transportation
B1531: 92900
B1532: EQUIPMENT MAINTENANCE AND REPAIR SERVICES FOR AGRICULTURAL,
B1533: CONSTRUCTION, HEAVY INDUSTRIAL, MATERIAL HANDLING, AND ROAD AND
B1534: HIGHWAY EQUIPMENT
B1535: NIGP
B1536: Code
B1537: Description
B1538: 92900
B1539: EQUIPMENT MAINTENANCE AND REPAIR SERVICES FOR
B1540: AGRICULTURAL, CONSTRUCTION, HEAVY INDUSTRIAL, MATERIAL
B1541: HANDLING, AND ROAD AND HIGHWAY EQUIPMENT
B1542: 92904 Agricultural Implements, Parts and Accessories Maintenance and Repair
B1543: 92912 Asphalt Distributors, Levelers, Mixers, etc. Maintenance and Repair
B1544: 92913 Asphalt Heaters Maintenance and Repair
B1545: 92914 Asphalt Pavers Maintenance and Repair
B1546: 92915 Asphalt Scarifiers, Milling Machines, Scrapers, etc., Maintenance and Repair
B1547: 92917 Automotive Shop Equipment Maintenance and Repair
B1548: 92924 Car Wash Equipment Maintenance and Repair
B1549: 92929 Concrete Equipment: Buckets, Screeding Machines, Curbers, Finishers, etc.,
B1550: Maintenance and Repair
... B1598: Description
B1599: 93100
B1600: EQUIPMENT MAINTENANCE AND REPAIR SERVICES FOR APPLIANCE,
B1601: ATHLETIC, CAFETERIA, FURNITURE, MUSICAL INSTRUMENTS, AND
B1602: SEWING EQUIPMENT
B1603: 93105 Amusement Park Ride Equipment Maintenance and Repair
B1604: 93107 Appliances and Equipment, Household, (Not Laundry or HVAC) Maintenance
B1605: and Repair
B1606: 93111 Athletic and Sporting Goods Equipment and Accessories (Shoulder Pads,
B1607: etc.), Maintenance and Repair
...

Sheet NIGP Codes
A1: The official NIGP Commodity Book is copyrighted material to be used for reference purposes only and may not be reproduced without a license from Periscope Holdings, Inc.
A2: Class | B2: Item | C2: Description
A3: =TEXT(5,"000") -> 005 | B3: =TEXT(0,"00") -> 00 | C3: ABRASIVES
A4: =TEXT(5,"000") -> 005 | B4: =TEXT(5,"00") -> 05 | C4: Abrasives Equipment and Tools
A5: =TEXT(5,"000") -> 005 | B5: =TEXT(14,"00") -> 14 | C5: Abrasives, Coated: Cloth, Fiber, Sandpaper, etc.
A6: =TEXT(5,"000") -> 005 | B6: =TEXT(21,"00") -> 21 | C6: Abrasives, Sandblasting, Metal
A7: =TEXT(5,"000") -> 005 | B7: =TEXT(28,"00") -> 28 | C7: Abrasives, Sandblasting, Other than Metal
A8: =TEXT(5,"000") -> 005 | B8: =TEXT(42,"00") -> 42 | C8: Abrasives, Solid: Wheels, Stones, etc.
A9: =TEXT(5,"000") -> 005 | B9: =TEXT(56,"00") -> 56 | C9: Abrasives, Tumbling (Wheel)
A10: =TEXT(5,"000") -> 005 | B10: =TEXT(63,"00") -> 63 | C10: Compounds, Grinding and Polishing: Carborundum, Diamond, etc. (See Class 075 For Valve Grinding Compounds)
A11: =TEXT(5,"000") -> 005 | B11: =TEXT(70,"00") -> 70 | C11: Pumice Stone (Inactive, effective January 1, 2016)
A12: =TEXT(5,"000") -> 005 | B12: =TEXT(75,"00") -> 75 | C12: Recycled Abrasives, Products and Supplies
A13: =TEXT(5,"000") -> 005 | B13: =TEXT(84,"00") -> 84 | C13: Wool, Steel, Aluminum, Copper, and Lead
A14: =TEXT(10,"000") -> 010 | B14: =TEXT(0,"00") -> 00 | C14: ACOUSTICAL TILE, INSULATING MATERIALS, AND SUPPLIES
A15: =TEXT(10,"000") -> 010 | B15: =TEXT(5,"00") -> 05 | C15: Acoustical Tile, All Types, Including Recycled Types
A16: =TEXT(10,"000") -> 010 | B16: =TEXT(8,"00") -> 08 | C16: Acoustical Tile Accessories: Channels, Grids, Mounting Hardware, Rods, Runners, Suspension Brackets, Tees, Wall Angles, and Wires
A17: =TEXT(10,"000") -> 010 | B17: =TEXT(9,"00") -> 09 | C17: Acoustical Tile Insulation
A18: =TEXT(10,"000") -> 010 | B18: =TEXT(11,"00") -> 11 | C18: Adhesives and Cements, Acoustical Tile
A19: =TEXT(10,"000") -> 010 | B19: =TEXT(14,"00") -> 14 | C19: Adhesives and Cements, Insulation
A20: =TEXT(10,"000") -> 010 | B20: =TEXT(17,"00") -> 17 | C20: Insulation, Aluminum Foil
A21: =TEXT(10,"000") -> 010 | B21: =TEXT(30,"00") -> 30 | C21: Hardware, Pipe Insulation: Bands, Clips, and Wires
A22: =TEXT(10,"000") -> 010 | B22: =TEXT(38,"00") -> 38 | C22: Hardware, Duct Insulation: Clips, Pins, etc.
A23: =TEXT(10,"000") -> 010 | B23: =TEXT(41,"00") -> 41 | C23: Insulation: Cork, Blocks, Boards, Sheets, etc.
A24: =TEXT(10,"000") -> 010 | B24: =TEXT(45,"00") -> 45 | C24: Insulation and Finish Systems, Exterior
A25: =TEXT(10,"000") -> 010 | B25: =TEXT(53,"00") -> 53 | C25: Insulation, Fiberglass: Batts, Blankets and Rolls
A26: =TEXT(10,"000") -> 010 | B26: =TEXT(56,"00") -> 56 | C26: Foam Glass: Blocks, Sheets, etc.
A27: =TEXT(10,"000") -> 010 | B27: =TEXT(57,"00") -> 57 | C27: Insulation, Foam-in-Place: Phenolic, Urethane, etc.
A28: =TEXT(10,"000") -> 010 | B28: =TEXT(59,"00") -> 59 | C28: Insulation, Foam Plastics: Blocks, Boards, Sheets, etc.
A29: =TEXT(10,"000") -> 010 | B29: =TEXT(61,"00") -> 61 | C29: Insulation, Reflective, Radiant Barrier
A30: =TEXT(10,"000") -> 010 | B30: =TEXT(62,"00") -> 62 | C30: Insulation, Interior
A31: =TEXT(10,"000") -> 010 | B31: =TEXT(63,"00") -> 63 | C31: Insulation, Blown Type
A32: =TEXT(10,"000") -> 010 | B32: =TEXT(64,"00") -> 64 | C32: Insulation, Loose Fill
A33: =TEXT(10,"000") -> 010 | B33: =TEXT(65,"00") -> 65 | C33: Insulation Jacketing, Canvas, Osnaburg, etc.
A34: =TEXT(10,"000") -> 010 | B34: =TEXT(70,"00") -> 70 | C34: Insulation, Magnesia, Blocks, Sheets, etc.
A35: =TEXT(10,"000") -> 010 | B35: =TEXT(72,"00") -> 72 | C35: Insulation, Mineral Wool: Blankets, Blocks, Boards
A36: =TEXT(10,"000") -> 010 | B36: =TEXT(75,"00") -> 75 | C36: Insulation Paints, Primers, Sealers, etc.
A37: =TEXT(10,"000") -> 010 | B37: =TEXT(76,"00") -> 76 | C37: Insulation, Paper Type Material, Cellulose, etc.
A38: =TEXT(10,"000") -> 010 | B38: =TEXT(78,"00") -> 78 | C38: Insulation, Pipe and Tubing, All Types
A39: =TEXT(10,"000") -> 010 | B39: =TEXT(81,"00") -> 81 | C39: Insulation, Preformed, All Types, Ells, Tees, Valves, etc.
A40: =TEXT(10,"000") -> 010 | B40: =TEXT(83,"00") -> 83 | C40: Recycled Insulation Materials and Supplies, All Types
A41: =TEXT(10,"000") -> 010 | B41: =TEXT(84,"00") -> 84 | C41: Insulation, Rubber
A42: =TEXT(15,"000") -> 015 | B42: =TEXT(0,"00") -> 00 | C42: ADDRESSING, COPYING, MIMEOGRAPH, AND DUPLICATING MACHINE SUPPLIES: CHEMICALS, INKS, PAPER, ETC.
A43: =TEXT(15,"000") -> 015 | B43: =TEXT(6,"00") -> 06 | C43: Addressing Machine Supplies, Metal and Plastic Plate Type
A44: =TEXT(15,"000") -> 015 | B44: =TEXT(10,"00") -> 10 | C44: Addressing Machine Supplies, Paper Plate Type
A45: =TEXT(15,"000") -> 015 | B45: =TEXT(15,"00") -> 15 | C45: Chemicals and Supplies, Dry, Bond Paper Type Copying Machines
A46: =TEXT(15,"000") -> 015 | B46: =TEXT(16,"00") -> 16 | C46: Chemicals and Supplies, Wet, Bond Paper Type Copying Machines
A47: =TEXT(15,"000") -> 015 | B47: =TEXT(20,"00") -> 20 | C47: Chemicals and Supplies, Duplicating Machines
A48: =TEXT(15,"000") -> 015 | B48: =TEXT(25,"00") -> 25 | C48: Chemicals, Inks, and Supplies, Mimeograph Machines)
A49: =TEXT(15,"000") -> 015 | B49: =TEXT(38,"00") -> 38 | C49: Paper, Chemicals, and Supplies, Blueline Machines
A50: =TEXT(15,"000") -> 015 | B50: =TEXT(39,"00") -> 39 | C50: Paper, Chemicals, and Supplies, Coated or Treated Paper Type Copying Machines, (See 305-39 for Diazo Process Copy Machines
A51: =TEXT(15,"000") -> 015 | B51: =TEXT(45,"00") -> 45 | C51: Paper, Chemicals, and Supplies, Diffusion Transfer Type Copying Machines, (See 305-39 for Diazo Process Copy Machines)
A52: =TEXT(15,"000") -> 015 | B52: =TEXT(55,"00") -> 55 | C52: Paper and Supplies, Dual Spectrum Process Copying Machines, (See 305-39 for Diazo Process Copy Machines)
A53: =TEXT(15,"000") -> 015 | B53: =TEXT(70,"00") -> 70 | C53: Paper, Chemicals, and Supplies. Thermal Process Copying Machines, (See 305-39 for Diazo Process Copy Machines)
A54: =TEXT(15,"000") -> 015 | B54: =TEXT(77,"00") -> 77 | C54: Recycled Copying and Duplicating Supplies
A55: =TEXT(19,"000") -> 019 | B55: =TEXT(0,"00") -> 00 | C55: AGRICULTURAL CROPS AND GRAINS, INCLUDING FRUITS, MELONS, NUTS, AND VEGETABLES
A56: =TEXT(19,"000") -> 019 | B56: =TEXT(20,"00") -> 20 | C56: Barley
A57: =TEXT(19,"000") -> 019 | B57: =TEXT(21,"00") -> 21 | C57: Berry Crops
A58: =TEXT(19,"000") -> 019 | B58: =TEXT(24,"00") -> 24 | C58: Buckwheat
A59: =TEXT(19,"000") -> 019 | B59: =TEXT(30,"00") -> 30 | C59: Corn
A60: =TEXT(19,"000") -> 019 | B60: =TEXT(32,"00") -> 32 | C60: Cotton
A61: =TEXT(19,"000") -> 019 | B61: =TEXT(41,"00") -> 41 | C61: Fruits, Citrus
A62: =TEXT(19,"000") -> 019 | B62: =TEXT(42,"00") -> 42 | C62: Fruits, Deciduous Tree
A63: =TEXT(19,"000") -> 019 | B63: =TEXT(47,"00") -> 47 | C63: Grapes
A64: =TEXT(19,"000") -> 019 | B64: =TEXT(50,"00") -> 50 | C64: Hops
A65: =TEXT(19,"000") -> 019 | B65: =TEXT(53,"00") -> 53 | C65: Melons
A66: =TEXT(19,"000") -> 019 | B66: =TEXT(54,"00") -> 54 | C66: Millet
A67: =TEXT(19,"000") -> 019 | B67: =TEXT(56,"00") -> 56 | C67: Nuts, Tree
A68: =TEXT(19,"000") -> 019 | B68: =TEXT(58,"00") -> 58 | C68: Oats
A69: =TEXT(19,"000") -> 019 | B69: =TEXT(60,"00") -> 60 | C69: Potatoes
A70: =TEXT(19,"000") -> 019 | B70: =TEXT(62,"00") -> 62 | C70: Pumpkins
A71: =TEXT(19,"000") -> 019 | B71: =TEXT(66,"00") -> 66 | C71: Rice
A72: =TEXT(19,"000") -> 019 | B72: =TEXT(67,"00") -> 67 | C72: Rye
A73: =TEXT(19,"000") -> 019 | B73: =TEXT(72,"00") -> 72 | C73: Sorghum
A74: =TEXT(19,"000") -> 019 | B74: =TEXT(73,"00") -> 73 | C74: Soybeans
A75: =TEXT(19,"000") -> 019 | B75: =TEXT(78,"00") -> 78 | C75: Sugarcane and Sugarbeets
A76: =TEXT(19,"000") -> 019 | B76: =TEXT(85,"00") -> 85 | C76: Tobacco
A77: =TEXT(19,"000") -> 019 | B77: =TEXT(90,"00") -> 90 | C77: Vegetables, (Not Otherwise Classified)
A78: =TEXT(19,"000") -> 019 | B78: =TEXT(94,"00") -> 94 | C78: Wheat
A79: =TEXT(20,"000") -> 020 | B79: =TEXT(0,"00") -> 00 | C79: AGRICULTURAL EQUIPMENT, IMPLEMENTS, AND ACCESSORIES (SEE CLASS 022 FOR PARTS)
A80: =TEXT(20,"000") -> 020 | B80: =TEXT(2,"00") -> 02 | C80: Backhoe, Farm Tractor
A81: =TEXT(20,"000") -> 020 | B81: =TEXT(4,"00") -> 04 | C81: Brush and Tree Chippers
A82: =TEXT(20,"000") -> 020 | B82: =TEXT(6,"00") -> 06 | C82: Brush Cutters and Saws, Motor Driven
A83: =TEXT(20,"000") -> 020 | B83: =TEXT(10,"00") -> 10 | C83: Counters, Acre
A84: =TEXT(20,"000") -> 020 | B84: =TEXT(13,"00") -> 13 | C84: Cultivating Equipment, Farm: Go-Devils, Row Type Shovel Cultivators, Tooth and Spring Harrows, etc.
A85: =TEXT(20,"000") -> 020 | B85: =TEXT(14,"00") -> 14 | C85: Curb Edger, Heavy Duty, Tractor Mounted
A86: =TEXT(20,"000") -> 020 | B86: =TEXT(15,"00") -> 15 | C86: Cutters and Shredders, Mowers, Heavy Duty, Flail: Tow Type and Center Mount Type
A87: =TEXT(20,"000") -> 020 | B87: =TEXT(16,"00") -> 16 | C87: Cutters and Shredders, Mowers, Heavy Duty, Reel and Rotary: Tow Type and Center Mount Type
A88: =TEXT(20,"000") -> 020 | B88: =TEXT(18,"00") -> 18 | C88: Dozer Blades. Farm Tractors
A89: =TEXT(20,"000") -> 020 | B89: =TEXT(20,"00") -> 20 | C89: Drying Equipment, Grain
A90: =TEXT(20,"000") -> 020 | B90: =TEXT(23,"00") -> 23 | C90: Ensilage Cutters
A91: =TEXT(20,"000") -> 020 | B91: =TEXT(25,"00") -> 25 | C91: Farm Wagons
A92: =TEXT(20,"000") -> 020 | B92: =TEXT(27,"00") -> 27 | C92: Feed Mills and Mixers
A93: =TEXT(20,"000") -> 020 | B93: =TEXT(28,"00") -> 28 | C93: Feed Wagons
A94: =TEXT(20,"000") -> 020 | B94: =TEXT(30,"00") -> 30 | C94: Fertilizer Applicators and Fittings: Liquid and Gas
A95: =TEXT(20,"000") -> 020 | B95: =TEXT(31,"00") -> 31 | C95: Fertilizer Distributors, Dry, Commercial (See Class 515 for Lawn Type Distributors)
A96: =TEXT(20,"000") -> 020 | B96: =TEXT(33,"00") -> 33 | C96: Garden Tractors, Cultivators, and Plows
A97: =TEXT(20,"000") -> 020 | B97: =TEXT(34,"00") -> 34 | C97: Gang Mowers, Reel Type, Towed
A98: =TEXT(20,"000") -> 020 | B98: =TEXT(35,"00") -> 35 | C98: Grain Bins and Tanks
A99: =TEXT(20,"000") -> 020 | B99: =TEXT(36,"00") -> 36 | C99: Grading Machines for Seeds, Grains and Dried Vegetables
A100: =TEXT(20,"000") -> 020 | B100: =TEXT(37,"00") -> 37 | C100: Grass Seed Strippers and Cleaners
...

Sheet Pre-processing File Requiements
A1: Proposed Layout for FPEM Input Records
A2: Payment Record
B3: Source Code | C3: Contract ID | D3: Org Code | E3: Event Code | F3: Event ID | G3: Accounting Date | H3: Curr. Code | I3: Tran Amount | J3: Account ID | K3: IP ID | L3: Fund Detail | M3: Object | N3: Sub Prog | O3: Party Name
B4: "PaymentSystem" | C4: if PO Number found for payment, PO Number Otherwise a dumb key | D4: Agency Key | E4: "Payment" | F4: Generated Unique ID for each record in file | G4: Date From File name | H4: "USD" | I4: Amount Field from File | J4: ? | K4: Vendor ID if Vendor Found on PO Data using Vendor name from payment, otherwise new Vendor ID for this Vendor Name | L4: Fund Detail from File | M4: Object From File | N4: Sub Prog from File | O4: Vendor Name from File
A7: PO Record
B9: Contract ID | C9: IP ID | D9: Party Name | E9: Org Code | F9: Event Code | G9: Event ID | H9: Account Date | I9: Source Code | J9: PO Number | K9: Product Description | L9: Quantity | M9: Unit of Measure | N9: Unit Price | O9: Account ID | P9: NIGP Code | Q9: NIGP Descript | R9: Unit of Measure Descript | S9: Vendor Part Num | T9: IP Address | U9: IP City | V9: IP State | W9: IP Country | X9: External IP ID | Y9: IP Postal Code | Z9: Ip Email Address
B10: PO Number from File | C10: Vendor ID Field in file | D10: Vendor Name | E10: Agency Key Code from Agency Name lookup | F10: "PurchaseOrder" | G10: PO Number + a number generated for each line | H10: Order Date | I10: "POSystem" | J10: Value from PO File | K10: Value from PO File | L10: Value from PO File | M10: Value from PO File | N10: Value from PO File | O10: Value from PO File | P10: Value from PO File | Q10: Value from PO File | R10: Value from PO File | S10: Value from PO File | T10: Value from PO File | U10: Value from PO File | V10: Value from PO File | W10: Value from PO File | Y10: Value from PO File | Z10: Value from PO File

Sheet Report Structures
B4: First View
C5: ARRANGEMENT_ TYPE_ CODE | D5: ARRANGEMENT_ TYPE_ DESCRIPTION | E5: COA ACCOUNT | F5: AMOUNT
C6: 4 | D6: REVENUE SOURCE | F6: XXX
C7: 5 | D7: EXPENSE SOURCE | F7: XXX
C8: 6 | D8: PO SOURCE | F8: XXX
B10: Drill Down View 1
C11: ARRANGEMENT_ TYPE_ CODE | D11: ARRANGEMENT_ TYPE_ DESCRIPTION | E11: COMMITMENT_ TYPE_ CODE | F11: COMMITMENT_ TYPE_ DESC | G11: AMOUNT
C12: 4 | D12: REVENUE | E12: 0 | F12: NO COMMITMENT | G12: XXX
C13: 5 | D13: EXPENSE | E13: 110 | F13: WITH PO | G13: XXX
C14: 5 | D14: EXPENSE | E14: 120 | F14: WITHOUT PO | G14: XXX
C15: 6 | D15: PO SOURCE | F15: PO ONLY | G15: XXX
C16: 6 | D16: PO SOURCE | F16: PO WITH PAYMENT | G16: XXX
B17: Drill Down View 2
C18: ARRANGEMENT_ TYPE_ CODE | D18: ARRANGEMENT_ TYPE_ DESCRIPTION | E18: COMMITMENT_ TYPE_ CODE | F18: COMMITMENT_ TYPE_ DESC | I18: AMOUNT
C19: 4 | D19: REVENUE | E19: 0 | F19: NO COMMITMENT | I19: XXX
C20: 5 | D20: EXPENSE | E20: 110 | F20: WITH PO | I20: XXX
C21: 5 | D21: EXPENSE | E21: 120 | F21: WITHOUT PO | I21: XXX

Sheet Univ. Journal
B3: Questions
B4: Sub Instrument ID?
B5: Recursive relationship for instruments?
B6: How much source IDs to add
B7: How many chart elements? Product, customer type, etc.?
B8: Platform processing date?
B9: Stat units, and quantity
B10: Position Hash
B13: Field Contents | C13: Field Name | D13: Field Name | E13: Disk Field Format | F13: Memory Field Format | G13: Field Content | H13: Length | I13: Description | J13: Sample Values | K13: Structure | L13: PO Example Field | M13: Payment Example Field
C14: Universal Journal | D14: Universal Journal | I14: Common on All Bus. Process
B15: Involved Party ID | C15: ujIPID | D15: ujIPID | E15: String | F15: Long | G15: Xref Key | H15: 15 | K15: Universal Journal | L15: VENDORID
B16: Instrument/Contract ID | C16: ujInstrumentID | D16: ujInstrumentID | E16: String | F16: Long | G16: Xref Key | K16: Universal Journal
B17: Instrument/Contract ID SubArrangement | C17: ujInstrumentID | D17: ujInstrumentID | E17: String | F17: Long | G17: Xref Key | K17: Universal Journal
B18: Business Event / Journal ID | C18: ujJrnlID | D18: ujJrnlID | E18: String | F18: Long | G18: Unique ID | I18: Unique identifier for each business event/universal journal | K18: Universal Journal
B19: Jrnl Line No | C19: ujJrnlLineID | D19: ujJrnlLineID | E19: String | F19: Int | G19: Unique ID | K19: Universal Journal
A20: x | B20: Business Event Code | C20: ujBusEventCD | D20: ujBusEventCD | E20: String | F20: Text | G20: Constant | H20: 16 | K20: Universal Journal
A21: x | B21: Source System ID | C21: ujSourceID | D21: ujSourceID | E21: String | F21: Text | G21: Constant | H21: 16 | I21: Identifier of system or system compoent that created the journal | K21: Universal Journal
A22: x | B22: Original Process ID | C22: ujProcessID | D22: ujProcessID | E22: String | F22: Text | G22: Constant | H22: 16 | I22: Identifier of system or system compoent that created the journal | K22: Universal Journal
A23: x | B23: Original Document ID | C23: ujOriginalDocID | D23: ujOriginalDocID | E23: String | F23: Text | H23: 50 | K23: Universal Journal | L23: PONUMBER
A24: x | B24: Journal / Event Description | C24: ujJrnlDescript | D24: ujJrnlDescript | E24: String | F24: Text | G24: Input Field | H24: 2000 | K24: Universal Journal
A25: x | B25: Ledger | C25: ujLedgerID | D25: ujLedgerID | E25: String | F25: Text | G25: Constant | H25: 16 | I25: BUD-OPERATING, BUD-CAPITAL, FIN, CMT | K25: Universal Journal
A26: x | B26: Jrnl Type | C26: ujJrnlType | D26: ujJrnlType | E26: String | F26: Text | G26: Constant | H26: 16 | J26: ANA - Analytical Journal, such as an allocation process STS - A Statistical Journal, containing a non-monetary value FRC - A Forecast Journal RCN - Reconciliation Balance used to agree to another ledger ACT - An Actual Financial Journal | K26: Universal Journal
A27: x | B27: Book-code / Basis | C27: ujBookCodeID | D27: ujBookCodeID | E27: String | F27: Text | G27: Constant | H27: 16 | K27: Universal Journal
A28: x | B28: Legal Entity (CO. / Owner) | C28: ujLegalEntityID | D28: ujLegalEntityID | E28: String | F28: Int | G28: Xref Key | H28: 16 | I28: Legal Entity, personal identifier | K28: Universal Journal | L28: AGENCY
A29: x | B29: Center ID | C29: ujCenterID | D29: ujCenterID | E29: String | F29: Int | G29: Xref Key | H29: 16 | I29: Cost or Profit Center | K29: Universal Journal
A30: x | B30: Affiliate Owner ID | C30: ujAffliateEntityID | D30: ujAffliateEntityID | E30: String | F30: Int | G30: Xref Key | H30: 16 | I30: Counterparty to transaction | K30: Universal Journal
A31: x | B31: Affliate Center ID | C31: ujAffliateCenterID | D31: ujAffliateCenterID | E31: String | F31: Int | G31: Xref Key | H31: 16 | K31: Universal Journal
A32: x | B32: Project ID | C32: ujProjectID | D32: ujProjectID | E32: String | F32: Int | G32: Xref Key | H32: 16 | K32: Universal Journal
A33: x | B33: Product / Material ID | C33: ujProductID | D33: ujProductID | E33: String | F33: Int | G33: Constant | K33: Universal Journal
A34: x | B34: Nominal Account | C34: ujAccountID | D34: ujAccountID | E34: String | F34: Int | G34: Xref Key | I34: Category of the journal, chart of account value | K34: Universal Journal
A35: x | B35: Alternate Account Code | C35: ujAltAccountID | D35: ujAltAccountID | E35: String | F35: Int | G35: Constant | K35: Universal Journal
A36: x | B36: Curr. Code Source | C36: ujCurrencyCodeSourceID | D36: ujCurrencyCodeSourceID | E36: String | F36: Text | G36: Constant | H36: 16 | K36: Universal Journal
A37: x | B37: Currency Type Code Source | C37: ujCurrencyTypeCodeSourceID | D37: ujCurrencyTypeCodeSourceID | E37: String | F37: Text | G37: Constant | H37: 16 | J37: Values include FN Functional, PR Presentation, TX Transaction | K37: Universal Journal
A38: x | B38: Curr. Code Target | C38: ujCurrencyCodeTargetID | D38: ujCurrencyCodeTargetID | E38: String | F38: Text | G38: Constant | H38: 16 | K38: Universal Journal
A39: x | B39: Currency Type Code Target | C39: ujCurrencyTypeCodeTargetID | D39: ujCurrencyTypeCodeTargetID | E39: String | F39: Text | G39: Constant | H39: 16 | J39: Values include FN Functional, PR Presentation, TX Transaction | K39: Universal Journal
A40: x | B40: Fiscal Period | C40: ujFiscalPeriod | D40: ujFiscalPeriod | E40: String | F40: Date | G40: Derived | K40: Universal Journal
A41: x | B41: Acctg. Date | C41: ujAcctDate | D41: ujAcctDate | E41: String | F41: Date | G41: Derived | K41: Universal Journal
A42: x | B42: Transaction Date | C42: ujTransDate | D42: ujTransDate | E42: String | F42: Date | G42: Input Field | K42: Universal Journal | L42: ORDEREDDATE
A43: x | B43: Process Date | C43: ujProcessDate | D43: ujProcessDate | E43: String | F43: Date | G43: Input Field | K43: Universal Journal | L43: ORDEREDDATE
B44: Movement Flag | C44: ujMovementFlg | D44: ujMovementFlg | E44: String | F44: Boolean | G44: Constant | H44: 1 | I44: Indicates if amount is a movement. If not, it is an accumulation | J44: y/n | K44: Universal Journal
B45: Direct vs. Offset Flag | C45: ujDirVsOffsetFlg | D45: ujDirVsOffsetFlg | E45: String | F45: Boolean | G45: Constant | H45: 1 | J45: d/o | K45: Universal Journal
B46: Reconciliable Flag | C46: ujReconcileFlg | D46: ujReconcileFlg | E46: String | F46: Boolean | G46: Constant | H46: 1 | I46: Indicates if associated balance can be reconciled elsewhere | J46: y/n | K46: Universal Journal
B47: Adjustment Flag | C47: ujAdjustFlg | D47: ujAdjustFlg | E47: String | F47: Boolean | G47: Constant | H47: 1 | I47: Indicates if journal is an adjustment as opposed to a automated feed | J47: y/n | K47: Universal Journal
A48: x | B48: Debit Credit Indicator | C48: ujDebitCreditFlg | D48: ujDebitCreditFlg | E48: String | F48: Boolean | G48: Constant | H48: 1 | K48: Universal Journal | L48: UNITOFMEASURECODE
A49: x | B49: Unit of Measure | C49: ujUnitOfMeasure | D49: ujUnitOfMeasure | E49: String | F49: Text | G49: Constant | H49: 50 | K49: Universal Journal | L49: UNITOFMEASURECODE
A50: x | B50: Uniit Price | C50: ujUnitPrice | D50: ujUnitPrice | E50: BigDecimal | F50: Number | G50: Value | K50: Universal Journal | L50: PRICE
A51: x | B51: Extended Amount | C51: ujExtendedAmount | D51: ujExtendedAmount | E51: BigDecimal | F51: Number | G51: Value
A52: x | B52: Transaction Amount | C52: ujTransAmount | D52: ujTransAmount | E52: BigDecimal | F52: Number | G52: Value | K52: Universal Journal
A53: x | B53: Statistical Amount/Quantity | C53: ujStatisticalAmount | D53: ujStatisticalAmount | E53: BigDecimal | F53: Number | G53: Value | K53: Universal Journal | L53: QUANTITYORDERED
B54: Rule Set ID | C54: ujRuleSetID | D54: ujRuleSetID | E54: String | F54: Text | G54: Constant | H54: 16 | K54: Universal Journal
B55: Rule ID | C55: ujRuleID | D55: ujRuleID | E55: String | F55: Text | G55: Constant | H55: 16 | K55: Universal Journal
B56: Audit Trial Extension ID | C56: ujExtensionIDAuditTrail | D56: ujExtensionIDAuditTrail | E56: String | F56: int | G56: Xref Key | K56: Universal Journal
B57: Source Extension ID | C57: ujExtensionIDSource | D57: ujExtensionIDSource | E57: String | F57: int | G57: Xref Key | K57: Universal Journal
B58: Classification Extension ID | C58: ujExtensionIDClass | D58: ujExtensionIDClass | E58: String | F58: int | G58: Xref Key | K58: Universal Journal
B59: Date Extension ID | C59: ujExtensionIDDates | D59: ujExtensionIDDates | E59: String | F59: int | G59: Xref Key | K59: Universal Journal
B60: Other Customization Ext ID | C60: ujExtensionIDCustom | D60: ujExtensionIDCustom | E60: String | F60: int | G60: Xref Key | K60: Universal Journal
A61: x | B61: Spot Exchange Rate | C61: ujSpotExchangeRate | D61: ujSpotExchangeRate | E61: BigDecimal | F61: Number | G61: Value | K61: Universal Journal
C62: Instrument/Contract | D62: Instrument/Contract | I62: Unique by Business Process
B63: Involved Party ID | C63: uiIPID | D63: uiIPID | E63: String | F63: Long | G63: Xref Key | K63: Universal Contract | L63: VENDORID
A64: x | B64: Instrument/Contract ID | C64: uiInstrumentID | D64: uiInstrumentID | E64: String | F64: Long | G64: Xref Key | K64: Universal Contract
A65: x | B65: Contract Type | C65: uiInstrumentType | D65: uiInstrumentType | E65: String | F65: Text | G65: Value | K65: Universal Contract
A66: x | B66: Contract Start Date | C66: uiInstrumentStattDate | D66: uiInstrumentStattDate | E66: String | F66: Date | G66: Blank | K66: Universal Contract | L66: ORDEREDDATE
C67: Invovled Party | D67: Invovled Party
A68: x | B68: Involved Party ID | C68: ipIPID | D68: ipIPID | E68: String | F68: Long | G68: Unique ID | K68: Involved Party | L68: VENDORID
A69: x | B69: IP Name | C69: ipName | D69: ipName | E69: String | F69: Text | G69: Value | H69: 128 | K69: Involved Party | L69: VENDORNAME
A70: x | B70: IP Address | C70: ipAddress | D70: ipAddress | E70: String | F70: Text | G70: Value | H70: 255 | K70: Involved Party | L70: VENDORADDRESS
A71: x | B71: IP City | C71: ipCity | D71: ipCity | E71: String | F71: Text | G71: Value | H71: 255 | K71: Involved Party | L71: VENDORCITY
A72: x | B72: IP State | C72: ipState | D72: ipState | E72: String | F72: Text | G72: Value | H72: 50 | K72: Involved Party | L72: VENDORSTATE
A73: x | B73: IP Country | C73: ipCountry | D73: ipCountry | E73: String | F73: Text | G73: Constant | H73: 255 | K73: Involved Party
A74: x | B74: IP Postal Code | C74: ipPostalCode | D74: ipPostalCode | E74: String | F74: Text | G74: Value | H74: 255 | K74: Involved Party | L74: VENDORPOSTALCODE
A75: x | B75: IP e-mail | C75: ipEmail | D75: ipEmail | E75: String | F75: Text | G75: Value | H75: 100 | K75: Involved Party | L75: VENDORLOC_EMAILADDRESS
A76: x | B76: IP Vendor ID | C76: ipExternalID | D76: ipExternalID | E76: String | F76: Int | G76: Value | H76: 15 | K76: Involved Party | L76: VENDORID
A77: x | B77: IP Unit ID: | C77: ipUnitID | D77: ipUnitID | E77: String | F77: Int | G77: Value | H77: 15 | K77: Involved Party
A78: x | B78: IP District ID: | C78: ipDistrictID | D78: ipDistrictID | E78: String | F78: Int | G78: Value | H78: 15 | K78: Involved Party
A79: x | B79: IP Source System ID | C79: ipSourceSystemID | D79: ipSourceSystemID | E79: String | F79: Int | G79: Value | H79: 15 | K79: Involved Party
C80: Trading Partners | D80: Trading Partners
B81: Involved Party ID | C81: tpIPID | D81: tpIPID | E81: String | F81: Long | G81: Xref Key | K81: Trading Partner
B82: Related IP IDs | C82: tpRelatedIPID | D82: tpRelatedIPID | E82: String | F82: Long | G82: Xref Key | K82: Trading Partner
C83: Universal Journal Extension | D83: Universal Journal Extension
C84: Original PO Transaction | D84: Original PO Transaction
B85: Involved Party ID | C85: ujepoIPID | D85: ujepoIPID | E85: String | F85: Long | G85: Xref Key | H85: 15 | K85: UJ PO Extension | L85: VENDORID
B86: Instrument/Contract ID | C86: ujepoInstrumentID | D86: ujepoInstrumentID | E86: String | F86: Long | G86: Xref Key | K86: UJ PO Extension
B87: Commitment ID | C87: ujepoCommitmentID | D87: ujepoCommitmentID | E87: String | F87: Long | G87: Xref Key | K87: UJ PO Extension
B88: Instrument ID | C88: ujepoInstID | D88: ujepoInstID | E88: String | F88: Long | G88: Unique ID | H88: 50 | K88: UJ PO Extension | L88: based on PO Num
B89: Business Event / Journal ID | C89: ujepoJrnlID | D89: ujepoJrnlID | E89: String | F89: Long | G89: Unique ID | K89: UJ PO Extension
B90: Jrnl Line No | C90: ujepoJrnlLineID | D90: ujepoJrnlLineID | E90: String | F90: Int | G90: Unique ID | K90: UJ PO Extension
B91: Source Extension ID | C91: ujepoExtensionIDSource | D91: ujepoExtensionIDSource | E91: String | F91: int | G91: Xref Key | K91: UJ PO Extension
B92: Order # | C92: ujepoPONumber | D92: ujepoPONumber | E92: String | F92: VARCHAR2 | H92: 50 | K92: UJ PO Extension | L92: PONUMBER
B93: Agency/Entity Description | C93: ujepoAgency | D93: ujepoAgency | E93: String | F93: VARCHAR2 | H93: 128 | K93: UJ PO Extension | L93: AGENCY
B94: Order Date | C94: ujepoOrderedDate | D94: ujepoOrderedDate | E94: String | F94: Date | G94: MM/DD/YYYY | K94: UJ PO Extension | L94: ORDEREDDATE
B95: Item Description | C95: ujepoVendorCommodityDesc | D95: ujepoVendorCommodityDesc | E95: String | F95: VARCHAR2 | H95: 2000 | K95: UJ PO Extension | L95: VENDORCOMMODITYDESC
B96: Quantity Ordered | C96: ujepoQuantityOrdered | D96: ujepoQuantityOrdered | E96: BigDecimal | F96: NUMBER | K96: UJ PO Extension | L96: QUANTITYORDERED
B97: Unit Price | C97: ujepoPrice | D97: ujepoPrice | E97: BigDecimal | F97: NUMBER | K97: UJ PO Extension | L97: PRICE
B98: Vendor DUNS # | C98: ujepoVendorID | D98: ujepoVendorID | E98: String | F98: VARCHAR2 | H98: 15 | K98: UJ PO Extension | L98: VENDORID
B99: Vendor Name (as shown on order) | C99: ujepoVendorName | D99: ujepoVendorName | E99: String | F99: VARCHAR2 | H99: 128 | K99: UJ PO Extension | L99: VENDORNAME
B100: Order Street | C100: ujepoVendorAddress | D100: ujepoVendorAddress | E100: String | F100: VARCHAR2 | H100: 255 | K100: UJ PO Extension | L100: VENDORADDRESS
B101: Order City | C101: ujepoVendorCity | D101: ujepoVendorCity | E101: String | F101: VARCHAR2 | H101: 255 | K101: UJ PO Extension | L101: VENDORCITY
B102: Order State | C102: ujepoVendorState | D102: ujepoVendorState | E102: String | F102: VARCHAR2 | H102: 50 | K102: UJ PO Extension | L102: VENDORSTATE
B103: Order Zip Code | C103: ujepoVendorPostalCode | D103: ujepoVendorPostalCode | E103: String | F103: VARCHAR2 | H103: 255 | K103: UJ PO Extension | L103: VENDORPOSTALCODE
B104: Order eMail Contact | C104: ujepoVendorLocEmailAddress | D104: ujepoVendorLocEmailAddress | E104: String | F104: VARCHAR2 | H104: 100 | K104: UJ PO Extension | L104: VENDORLOC_EMAILADDRESS
...

Sheet VA Data Structures
B1: This sheet has column headings from the files downloaded from the state of VA; it notes data structure changes that need to be made
A3: F03 | B3: Q1 | C3: EXP | F3: AGY_AGENCY_KEY | G3: FNDDTL_FUND_DETAIL_KEY | H3: OBJ_OBJECT_KEY | I3: SPRG_SUB_PROGRAM_KEY | J3: VENDOR_NAME | K3: AMOUNT | N3: Agency crosswalk File
F4: 267 | G4: 1552 | H4: 56 | I4: 2701 | J4: BLACKWELLS BOOK SERVICES | K4: 271.93 | N4: AGY_AGENCY_CODE | O4: AGY_AGENCY_KEY | P4: AGY_AGENCY_NAME
B5: Q2 | D5: txt | F5: AGY_AGENCY_KEY | G5: FNDDTL_FUND_DETAIL_KEY | H5: OBJ_OBJECT_KEY | I5: SPRG_SUB_PROGRAM_KEY | J5: VENDOR_NAME | K5: AMOUNT | N5: X00 | O5: 299 | P5: Private College or University
B6: Q3 | F6: AGY_AGENCY_KEY | G6: FNDDTL_FUND_DETAIL_KEY | H6: OBJ_OBJECT_KEY | I6: SPRG_SUB_PROGRAM_KEY | J6: VENDOR_NAME | K6: AMOUNT | N6: 722 | O6: 300 | P6: Office of Inspector General Mental Health
B7: Q4 | F7: AGY_AGENCY_KEY | G7: FNDDTL_FUND_DETAIL_KEY | H7: OBJ_OBJECT_KEY | I7: SPRG_SUB_PROGRAM_KEY | J7: VENDOR_NAME | K7: AMOUNT | N7: 778 | O7: 301 | P7: Department of Forensic Science
A8: F04 | B8: Q1 | F8: AGY_AGENCY_KEY | G8: FNDDTL_FUND_DETAIL_KEY | H8: OBJ_OBJECT_KEY | I8: SPRG_SUB_PROGRAM_KEY | J8: VENDOR_NAME | K8: AMOUNT
B9: Q2 | F9: AGY_AGENCY_KEY | G9: FNDDTL_FUND_DETAIL_KEY | H9: OBJ_OBJECT_KEY | I9: SPRG_SUB_PROGRAM_KEY | J9: VENDOR_NAME | K9: AMOUNT | N9: Ref Fund Detail
B10: Q3 | F10: AGY_AGENCY_KEY | G10: FNDDTL_FUND_DETAIL_KEY | H10: OBJ_OBJECT_KEY | I10: SPRG_SUB_PROGRAM_KEY | J10: VENDOR_NAME | K10: AMOUNT | N10: FNDDTL_FUND_DETAIL_KEY | O10: FNDDTL_FUND_DETAIL_NAME
B11: Q4 | F11: AGY_AGENCY_KEY | G11: FNDDTL_FUND_DETAIL_KEY | H11: OBJ_OBJECT_KEY | I11: SPRG_SUB_PROGRAM_KEY | J11: VENDOR_NAME | K11: AMOUNT | N11: 5525 | O11: DEBT SERVICE FEDERAL MATCH
N12: 5597 | O12: DEBT SERVICE FEDERAL MATCH
A13: F06 | F13: AGY_AGENCY_KEY | G13: FNDDTL_FUND_DETAIL_KEY | H13: OBJ_OBJECT_KEY | I13: SPRG_SUB_PROGRAM_KEY | J13: VENDOR_NAME | K13: AMOUNT | N13: 5650 | O13: DEBT SERVICE FEDERAL MATCH
A15: F08 | F15: AGY_AGENCY_KEY | G15: FNDDTL_FUND_DETAIL_KEY | H15: OBJ_OBJECT_KEY | I15: SPRG_SUB_PROGRAM_KEY | J15: VENDOR_NAME | K15: AMOUNT | N15: Ref obj key
N16: OBJ_OBJECT_KEY | O16: OBJ_OBJECT_NAME
A17: F09 | F17: AGY_AGENCY_KEY | G17: FNDDTL_FUND_DETAIL_KEY | H17: OBJ_OBJECT_KEY | I17: SPRG_SUB_PROGRAM_KEY | J17: VENDOR_NAME | K17: AMOUNT | N17: 67 | O17: OUTBOUND FREIGHT SERVICES
N18: 93 | O18: ORGANIZATION MEMBERSHIPS
A19: F10 | F19: Missing Exp Data | N19: 130 | O19: DENTAL SERVICES
N20: 150 | O20: FISCAL SERVICES
A21: F11 | F21: AGY_AGENCY_KEY | G21: FNDDTL_FUND_DETAIL_KEY | H21: OBJ_OBJECT_KEY | I21: SPRG_SUB_PROGRAM_KEY | J21: VENDOR_NAME | K21: AMOUNT
N22: Ref sub Program
A23: F12 | F23: AGY_AGENCY_KEY | G23: FNDDTL_FUND_DETAIL_KEY | H23: OBJ_OBJECT_KEY | I23: SPRG_SUB_PROGRAM_KEY | J23: VENDOR_NAME | K23: AMOUNT | L23: VOUCHER_DATE | N23: SPRG_SUB_PROGRAM_KEY | O23: SPRG_SUB_PROGRAM_NAME
N24: 3432 | O24: ADMINISTRATIVE AND SUPPORT SERVICES
A25: F13 | F25: AGY_AGENCY_KEY | G25: FNDDTL_FUND_DETAIL_KEY | H25: OBJ_OBJECT_KEY | I25: SPRG_SUB_PROGRAM_KEY | J25: VENDOR_NAME | K25: AMOUNT | L25: VOUCHER_DATE | N25: 3508 | O25: AIRPORT ASSISTANCE
N26: 3581 | O26: INFORMATION SYSTEMS MANAGEMENT AND DIRECTION
A27: F14 | D27: csv | F27: AGY_AGENCY_KEY | G27: AMOUNT | H27: FNDDTL_FUND_DETAIL_KEY | I27: OBJ_OBJECT_KEY | J27: SPRG_SUB_PROGRAM_KEY | K27: VENDOR_NAME | L27: VOUCHER_DATE | N27: 3595 | O27: ADMINISTRATIVE AND SUPPORT SERVICES
F28: 210 | G28: 61.36 | H28: 1401 | I28: 268 | J28: 4172 | K28: AGENCY TRANSACTION VOUCHER | L28: 41500
A29: F15 | F29: AGY_AGENCY_KEY | G29: AMOUNT | H29: FNDDTL_FUND_DETAIL_KEY | I29: OBJ_OBJECT_KEY | J29: SPRG_SUB_PROGRAM_KEY | K29: VENDOR_NAME | L29: VOUCHER_DATE
F32: More information available at: | H32: Overall COA definition | I32: http://www.doa.virginia.gov/reference/CAPP/CAPP_Topics_Cardinal/60101.pdf
H33: Fund details | I33: http://www.doa.virginia.gov/reference/CAPP/CAPP_Topics_Cardinal/60104.pdf
H34: Program (not one of the above) | I34: http://www.doa.virginia.gov/reference/CAPP/CAPP_Topics_Cardinal/60105.pdf
H35: Higher Level Link page | I35: http://www.doa.virginia.gov/reference/CAPP/CAPP_Summary_Cardinal.shtml
H37: Data downlaoded from | I37: http://datapoint.apa.virginia.gov
H39: Requested data from: | I39: webmaster@apa.virginia.gov
J40: http://www.doa.virginia.gov/reference/CAPP/CAPP_Topics_Cardinal/70210.pdf
J41: - Actuals Ledger Extract GL.288A This interface extracts posted summarized transactions from the actuals ledger in Cardinal.
J42: - COA Extract GL.102A This interface extracts valid chart of account information from each of the ChartField tables in Cardinal that are applicable for use.
J43: - Journal Extract GL.595 This interface extracts posted journal data from the journal tables to help agencies reconcile. Journal data will include journals entered online, sub module journals, spreadsheet journal upload, journal upload, CIPPS payroll journal, FAACS journals, and DOA entered journals.
J45: http://www.cardinalproject.virginia.gov/Cardinal%20Interfaces.shtml

Sheet VA PO Example Data
A2: PONUMBER | B2: AGENCY | C2: ORDEREDDATE | D2: VENDORCOMMODITYDESC | E2: QUANTITYORDERED | F2: PRICE | G2: VENDORID | H2: VENDORNAME | I2: VENDORADDRESS | J2: VENDORCITY | K2: VENDORSTATE | L2: VENDORPOSTALCODE | M2: VENDORLOC_EMAILADDRESS | N2: NIGPCODE | O2: NIGPDESCRIPTION | P2: UOMCode | Q2: UOMDesc | R2: VENDORPARTNUMBER
A3: EP2494035-V2 | B3: Department of Juvenile Justice | C3: 42719 | D3: CORE DEPOSIT | E3: 0 | F3: 18 | G3: 157706706 | H3: POWHATAN AUTO AND TRACTOR PARTS INC | I3: 3350 ANDERSON HWY. | J3: POWHATAN | K3: VA | L3: 23139 | M3: rabarden@aol.com | N3: 2000 | O3: AGRICULTURAL EQUIPMENT, IMPLEMENTS, AND ACCESSORIES (SEE CLASS 022 FOR PARTS) | P3: EA | Q3: each | R3: 7526R
A4: PCO1993812-V2 | B4: Department for Aging and Rehabilitative Services | C4: 42719 | D4: Supplier: PCI, Shipping:Freight By Amt | E4: 0 | F4: 10 | G4: 784338654 | H4: BELTWAY SUPPLY INC | I4: 7411 Alban Station Court Suite A102 | J4: Springfield | K4: VA | L4: 22150 | M4: dave@beltwaysupply.com | N4: 96286 | O4: Transportation of Goods and Other Freight Services | P4: EA | Q4: each | R4: Shipping
A5: PCO1993812-V2 | B5: Department for Aging and Rehabilitative Services | C5: 42719 | D5: 7/8&quot; SPLIT KEY RING 50/PK | E5: 0 | F5: 9.31 | G5: 784338654 | H5: BELTWAY SUPPLY INC | I5: 7411 Alban Station Court Suite A102 | J5: Springfield | K5: VA | L5: 22150 | M5: dave@beltwaysupply.com | N5: 45055 | O5: Locks, Key Blanks, and Locksmith Tools (Including Time Locks) | P5: EA | Q5: each | R5: 789406
A6: PCO2086371-V2 | B6: Virginia Department of Health | C6: 42894 | D6: PRINTER,WIDE FMT,OJ7612EAIO | E6: 0 | F6: 300.44 | G6: 12338837 | H6: ACCESS OFFICE PRODUCTS LLC | I6: 6 W Cary Street | J6: Richmond | K6: VA | L6: 23220 | M6: aj@accessofficeproducts.com | N6: 60557 | O6: Paper Trimmers, Hand, Rotary Type | P6: EA | Q6: each | R6: HEWG1X85A
A7: EP2581398 | B7: Virginia Department of Health | C7: 42894 | D7: Framing AC units, replace air conditioner, replace door | E7: 1 | F7: 2010.75 | G7: 16345130 | H7: HILL TOP CONTRACTORS LLC | I7: PO Box 241 | J7: Troutville | K7: VA | L7: 24175-0241 | M7: john@hilltopcontractors.org | N7: 3105 | O7: Air Conditioners (Cooling and Cooling/Heating Types): Window and Wall Mounted, and Parts and Accessories Not Individually Itemized | P7: EA | Q7: each
A8: EP2581399 | B8: Department of Conservation and Recreation | C8: 42894 | D8: Van Costs, Water Charges, Rental Houses, Grab & Go Food sold for VCLF | E8: 1 | F8: 4683.22 | G8: DB0039520 | H8: VIRGINIA CONSERVATION LEGACY FUND INC | I8: PO Box 87 | J8: Natural Bridge | K8: VA | L8: 24578-0087 | M8: Jennifer.Bell@Kissito.org | N8: 95294 | O8: Transportation Services For the Elderly, Handicapped, Incapacitated, Prisoners, Juries, etc. | P8: EA | Q8: each
A9: A181_170000647 | B9: Department of Labor and Industry | C9: 42894 | D9: SKC PASSIVE SAMPLERS FOR FORMALDEHYDE PACK/10 BUYER WILL CONTACT VENDOR WITH CREDIT CARD FOR PAYMENT OF INVOICE. | E9: 1 | F9: 239.55 | G9: 109909569 | H9: COLONIAL SCIENTIFIC INC | I9: 2015 W. Laburnum Ave | J9: RICHMOND | K9: VA | L9: 23227 | M9: dillon.barnett@colonialscientific.com | N9: 11519 | O9: Culture Media, Prepared (For Microbial Cultures See 495-38) | P9: PK | Q9: pack | R9: UMEX 100
A10: A181_170000648 | B10: Department of Labor and Industry | C10: 42894 | D10: EAR PLUGS, 32DB, CORDLESS, UNIVERSAL, DISPOSABLE, 200 PER PACK BUYER WILL CONTACT VENDOR WITH CREDIT CARD FOR PAYMENT OF INVOICE. | E10: 2 | F10: 26.63 | G10: 109909569 | H10: COLONIAL SCIENTIFIC INC | I10: 2015 W. Laburnum Ave | J10: RICHMOND | K10: VA | L10: 23227 | M10: dillon.barnett@colonialscientific.com | N10: 26952 | O10: Eye, Ear, Nose, and Throat Preparations | P10: BX | Q10: box | R10: 99-G1283-204
A11: A181_170000652 | B11: Department of Labor and Industry | C11: 42894 | D11: HEWLETT PACKARD PRINT CARTRIDGE QUOTE NO. 0000325 BUYER WILL CONTACT THE VENDOR WITH A CHARGE CARD FOR PAYMENT OF INVOICE. | E11: 1 | F11: 307.44 | G11: 79774525 | H11: ABACUS OFFICE SOLUTIONS LLC | I11: PO Box 25024 | J11: Richmond | K11: VA | L11: 23260-5024 | M11: admin@abacusofficesolutions.com | N11: 20772 | O11: Printer Accessories and Supplies: Chemicals, Forms Tractors, Inks and Cartridges, Paper, Label Sheets, Sheet Feeders, Toner Cartridges, Wheels, etc. | P11: EA | Q11: each | R11: HEW-C8543X
A12: A181_170000653 | B12: Department of Labor and Industry | C12: 42894 | D12: DELL TONER CRTDG, LSR - 2150CD, 2155, BK, 3K HIGH YIELD" QUOTE NO. 007214 BUYER WILL CONTACT VENDOR WITH CREDIT CARD FOR PAYMENT OF INVOICE." | E12: 2 | F12: 121.15 | G12: 929720183 | H12: TRI-CITY OFFICE PRODUCTS INC | I12: 2100 Westmoreland St. | J12: Richmond | K12: VA | L12: 23230 | M12: Teresa@tcopi.com | N12: 20772 | O12: Printer Accessories and Supplies: Chemicals, Forms Tractors, Inks and Cartridges, Paper, Label Sheets, Sheet Feeders, Toner Cartridges, Wheels, etc. | P12: EA | Q12: each | R12: DLLN51XP
A13: A181_170000653 | B13: Department of Labor and Industry | C13: 42894 | D13: DELL TONER CRTDG, CYN,2.5K | E13: 2 | F13: 119.98 | G13: 929720183 | H13: TRI-CITY OFFICE PRODUCTS INC | I13: 2100 Westmoreland St. | J13: Richmond | K13: VA | L13: 23230 | M13: Teresa@tcopi.com | N13: 20772 | O13: Printer Accessories and Supplies: Chemicals, Forms Tractors, Inks and Cartridges, Paper, Label Sheets, Sheet Feeders, Toner Cartridges, Wheels, etc. | P13: EA | Q13: each | R13: DLL769T5
A14: A181_170000653 | B14: Department of Labor and Industry | C14: 42894 | D14: DELL TONER CRTDG, LSR, MA, 2.5K | E14: 2 | F14: 119.98 | G14: 929720183 | H14: TRI-CITY OFFICE PRODUCTS INC | I14: 2100 Westmoreland St. | J14: Richmond | K14: VA | L14: 23230 | M14: Teresa@tcopi.com | N14: 20772 | O14: Printer Accessories and Supplies: Chemicals, Forms Tractors, Inks and Cartridges, Paper, Label Sheets, Sheet Feeders, Toner Cartridges, Wheels, etc. | P14: EA | Q14: each | R14: DLL8WNV5
A15: A181_170000653 | B15: Department of Labor and Industry | C15: 42894 | D15: DELL TONER, CRTDG, LSD, YW, 2.5K | E15: 2 | F15: 119.98 | G15: 929720183 | H15: TRI-CITY OFFICE PRODUCTS INC | I15: 2100 Westmoreland St. | J15: Richmond | K15: VA | L15: 23230 | M15: Teresa@tcopi.com | N15: 20772 | O15: Printer Accessories and Supplies: Chemicals, Forms Tractors, Inks and Cartridges, Paper, Label Sheets, Sheet Feeders, Toner Cartridges, Wheels, etc. | P15: EA | Q15: each | R15: DLLNPDXG
A16: DO1908516 | B16: College of William and Mary | C16: 42894 | D16: W0199034 - FURNITURE RENTAL - SUNKEN | E16: 1 | F16: 3954.5 | G16: 101363083 | H16: WILLIAMSBURG EVENT RENTALS | I16: 4403 Ironbound Rd. | J16: Williamsburg | K16: VA | L16: 23188 | M16: jennifer@williamsburgeventrentals.com | N16: 98172 | O16: Tents, Tarpaulins and Supplies Rental or Lease | P16: LO | Q16: lot
A17: EP2581401 | B17: Rappahannock Community College | C17: 42894 | D17: May 2017 Human Scoring of Essays for the VPT Invoice 19615, 5/31/17 | E17: 3 | F17: 9 | G17: 571172192 | H17: MCCANN ASSOCIATES HOLDING LLC | I17: 444 Oxford Valley Road | J17: Langhorne | K17: PA | L17: 19047 | M17: ecupingood@vantage.com | N17: 90783 | O17: Testing Services | P17: EA | Q17: each
A18: PCO2087329 | B18: Greensville Correctional Center | C18: 42894 | D18: Summer Hat, Sheriff Style, Navy Blue Size 7, Item Number: S-24 | E18: 5 | F18: 55.03 | G18: 828613062 | H18: PROCUREMENT SPECIALISTS, LLC | I18: 10201 Fairview Road | J18: Partlow | K18: VA | L18: 22534 | M18: hellzprwln@aol.com | N18: 20088 | O18: Uniforms, Wool and Woolen Blends | P18: EA | Q18: each
A19: PCO1992467-V2 | B19: Keen Mountain Correctional Center | C19: 42719 | D19: OIL FILTER 51734 | E19: 3 | F19: 12.34 | G19: 83055087 | H19: KIDD TIRE AUTO PARTS | I19: 127 Walnut Street | J19: North Tazewell | K19: VA | L19: 24630 | M19: mkidd@kiddtire.com | N19: 55734 | O19: Filters: Air, Fuel, Oil, etc. | P19: EA | Q19: each
A20: EP2509505-V3 | B20: Department of Juvenile Justice | C20: 42895 | D20: BlanketPOforServicesinDJJ'sEasternandSouthernRegionsfrom ********* 017 TransitionalServicesprovidedunderCC611 | E20: 1 | F20: 280000 | G20: 86462264 | H20: AMIKIDS INC | I20: 5915 BENJAMIN CENTER DRIVE | J20: TAMPA | K20: FL | L20: 33634 | M20: AMIkidsRFP@amikids.org | N20: 95221 | O20: Counseling | P20: EA | Q20: each
A21: PCO1995415 | B21: Keen Mountain Correctional Center | C21: 42719 | D21: 2550309, (120/Bx) Denture Cups Lt Blue | E21: 1 | F21: 159.99 | G21: 12430880 | H21: HENRY SCHEIN INC | I21: 135 DURYEA RD E115 | J21: MELVILLE | K21: NY | L21: 11747 | M21: biddept@henryschein.com | N21: 26000 | O21: DENTAL EQUIPMENT AND SUPPLIES | P21: EA | Q21: each
A22: PCO1995415 | B22: Keen Mountain Correctional Center | C22: 42719 | D22: 7773622, (3/Pk) Sof-Lex Pop-On Mandrel | E22: 1 | F22: 28.39 | G22: 12430880 | H22: HENRY SCHEIN INC | I22: 135 DURYEA RD E115 | J22: MELVILLE | K22: NY | L22: 11747 | M22: biddept@henryschein.com | N22: 26000 | O22: DENTAL EQUIPMENT AND SUPPLIES | P22: EA | Q22: each
A23: PCO1995415 | B23: Keen Mountain Correctional Center | C23: 42719 | D23: 1001313, (500/CA) DRI-GARD TOWEL 2PLYXPLY | E23: 1 | F23: 25.59 | G23: 12430880 | H23: HENRY SCHEIN INC | I23: 135 DURYEA RD E115 | J23: MELVILLE | K23: NY | L23: 11747 | M23: biddept@henryschein.com | N23: 26000 | O23: DENTAL EQUIPMENT AND SUPPLIES | P23: EA | Q23: each
A24: PCO1995415 | B24: Keen Mountain Correctional Center | C24: 42719 | D24: 5556743, (50/Jr) DISPERSALLOY CAPS REG SET | E24: 1 | F24: 205.19 | G24: 12430880 | H24: HENRY SCHEIN INC | I24: 135 DURYEA RD E115 | J24: MELVILLE | K24: NY | L24: 11747 | M24: biddept@henryschein.com | N24: 26000 | O24: DENTAL EQUIPMENT AND SUPPLIES | P24: EA | Q24: each
A25: PCO1995415 | B25: Keen Mountain Correctional Center | C25: 42719 | D25: 7724177, (100/Bx) MIDWEST CARBIDE BUR | E25: 1 | F25: 155.19 | G25: 12430880 | H25: HENRY SCHEIN INC | I25: 135 DURYEA RD E115 | J25: MELVILLE | K25: NY | L25: 11747 | M25: biddept@henryschein.com | N25: 26000 | O25: DENTAL EQUIPMENT AND SUPPLIES | P25: EA | Q25: each
A26: PCO1995415 | B26: Keen Mountain Correctional Center | C26: 42719 | D26: 6007970, CARVER DE WILAND 8 #7 HANDLE | E26: 1 | F26: 27.83 | G26: 12430880 | H26: HENRY SCHEIN INC | I26: 135 DURYEA RD E115 | J26: MELVILLE | K26: NY | L26: 11747 | M26: biddept@henryschein.com | N26: 26000 | O26: DENTAL EQUIPMENT AND SUPPLIES | P26: EA | Q26: each
A27: PCO1995415 | B27: Keen Mountain Correctional Center | C27: 42719 | D27: 7774656, (25/bx) ATTEST BIOLOGICAL MONITOR 48 HR AMPULE | E27: 1 | F27: 87.99 | G27: 12430880 | H27: HENRY SCHEIN INC | I27: 135 DURYEA RD E115 | J27: MELVILLE | K27: NY | L27: 11747 | M27: biddept@henryschein.com | N27: 26000 | O27: DENTAL EQUIPMENT AND SUPPLIES | P27: EA | Q27: each
... A30: PCO1992467-V2 | B30: Keen Mountain Correctional Center | C30: 42719 | D30: OIL FILTER 51356 | E30: 1 | F30: 4.35 | G30: 83055087 | H30: KIDD TIRE AUTO PARTS | I30: 127 Walnut Street | J30: North Tazewell | K30: VA | L30: 24630 | M30: mkidd@kiddtire.com | N30: 55734 | O30: Filters: Air, Fuel, Oil, etc. | P30: EA | Q30: each
A31: EP2499825 | B31: Virginia Western Community College | C31: 42739 | D31: Knee joint w/removable muscles 3B-A882 | E31: 4 | F31: 380.62 | G31: 79095242 | H31: DOVE MEDICAL SUPPLY LLC | I31: 8164 Mabe Marshall Road | J31: Summerfield | K31: NC | L31: 27358 | M31: lynnebridges@dovemedicalsupply.com | N31: 49043 | O31: Laboratory and Scientific Equipment and Supplies (Not Otherwise Classified) | P31: EA | Q31: each | R31: 3B-A882
A32: EP2499825 | B32: Virginia Western Community College | C32: 42739 | D32: Hip joint 7-part 3B-A881 | E32: 4 | F32: 324.62 | G32: 79095242 | H32: DOVE MEDICAL SUPPLY LLC | I32: 8164 Mabe Marshall Road | J32: Summerfield | K32: NC | L32: 27358 | M32: lynnebridges@dovemedicalsupply.com | N32: 49043 | O32: Laboratory and Scientific Equipment and Supplies (Not Otherwise Classified) | P32: EA | Q32: each | R32: 3B-A881
A33: PCO1992467-V2 | B33: Keen Mountain Correctional Center | C33: 42719 | D33: FUEL FILTER 33263 | E33: 2 | F33: 6.23 | G33: 83055087 | H33: KIDD TIRE AUTO PARTS | I33: 127 Walnut Street | J33: North Tazewell | K33: VA | L33: 24630 | M33: mkidd@kiddtire.com | N33: 55734 | O33: Filters: Air, Fuel, Oil, etc. | P33: EA | Q33: each
A34: EP2494460 | B34: Virginia Commonwealth University | C34: 42719 | D34: Bill for Richmond November/December 2016 Training Manuals: Phonics Boxes 1,2,& 3. Shipping included in the price. | E34: 1 | F34: 0 | G34: 156488640 | H34: NIEMANVILLE LLC | I34: 18 Alden Terrace | J34: Millbrook | K34: NY | L34: 12545 | M34: dnieman@optonline.net | N34: 92400 | O34: EDUCATIONAL/TRAINING SERVICES | P34: EA | Q34: each
A35: PCO1995438 | B35: Mountain Empire Community College | C35: 42719 | D35: Oil for Destroyit 2604 CC Shredder, #ACCED21/4 | E35: 1 | F35: 92.92 | G35: 14494991 | H35: VIRGINIA BUSINESS SYSTEMS | I35: 9899 MAYLAND DRIVE | J35: RICHMOND | K35: VA | L35: 23233 | M35: dgregg@vabs.net | N35: 61560 | O35: Office Supplies, General (Not Otherwise Classified) | P35: P4 | Q35: four pack | R35: ACCED21/4
A36: EP2494457 | B36: Rappahannock Community College | C36: 42719 | D36: Mini Blinds - 31x 72 & 31 x 72 for WC White PVC-vinyl | E36: 8 | F36: 21.5 | G36: 79725570 | H36: TC JONES DISTRIBUTING | I36: 6497 Tammy Ln | J36: Mechanicsville | K36: VA | L36: 23111-3367 | M36: TCJONESDISTRIBUTING@GMAIL.COM | N36: 87070 | O36: Vertical Blinds, All Types | P36: EA | Q36: each
A37: EP2494457 | B37: Rappahannock Community College | C37: 42719 | D37: Shipping | E37: 1 | F37: 26.75 | G37: 79725570 | H37: TC JONES DISTRIBUTING | I37: 6497 Tammy Ln | J37: Mechanicsville | K37: VA | L37: 23111-3367 | M37: TCJONESDISTRIBUTING@GMAIL.COM | N37: 96286 | O37: Transportation of Goods and Other Freight Services | P37: EA | Q37: each
A38: PCO1995405 | B38: Department of General Services | C38: 42719 | D38: 2 DIFFERENT SIZE BELTS FOR PHB AHUS AND LARGE TRASH BAGS FOR MECH ROOMS | E38: 1 | F38: 778.82 | G38: 837637990 | H38: RE REPLACEMENT PARTS | I38: 612 South Sycamore St | J38: PETERSBURG | K38: VA | L38: 23803 | M38: sales@repartsinc.com | N38: 3100 | O38: AIR CONDITIONING, HEATING, AND VENTILATING EQUIPMENT, PARTS AND ACCESSORIES (SEE CLASS 740 ALSO) | P38: LO | Q38: lot
A39: PCO1995402 | B39: Virginia Commonwealth University | C39: 42719 | D39: Annual inspection of JLG personnel lift | E39: 1 | F39: 305 | G39: 809401409 | H39: COLONIAL POWERLIFT INC | I39: P.O. Box 3576 | J39: Williamsburg | K39: VA | L39: 23187-3576 | M39: office@colonialpowerlift.com | N39: 96145 | O39: Inspection and Certification Services | P39: EA | Q39: each
A40: PCO1995403 | B40: Department of General Services | C40: 42719 | D40: Equipment repair at DCLS. | E40: 1 | F40: 3702.94 | G40: 23922545 | H40: RUTHERFORD JANITOR SUPPLY | I40: 1101 E. LABURNUM AVE | J40: RICHMOND | K40: VA | L40: 23222 | M40: sboone@rutherfordsupply.com | N40: 93800 | O40: EQUIPMENT MAINTENANCE AND REPAIR SERVICES FOR HOSPITAL, LABORATORY, AND TESTING EQUIPMENT | P40: EA | Q40: each
A41: EP2494447 | B41: Department of General Services | C41: 42719 | D41: Provide replacement drive for VDOT Central elevator P2 ASAP for building operation. Provide OEM unit set up by factory to original job specifications and provide revised job prints accordingly. Reference Otis August 26, 2016 quote by Mr. Eric Boyer. Additional negotiated work per contract. | E41: 1 | F41: 11319 | G41: 859800211 | H41: OTIS ELEVATOR CO | I41: 1642 Ownby Lane | J41: Richmond | K41: VA | L41: 23220-1317 | M41: kerrie.roslund@otis.com | N41: 91013 | O41: Elevator Installation, Maintenance and Repair | P41: LO | Q41: lot
A42: PCO1995404 | B42: Department of General Services | C42: 42719 | D42: upgrade panel 112 at the Library of VA | E42: 1 | F42: 12909.06 | G42: 10032969 | H42: JOHNSON CONTROLS INC | I42: 2315 Commerce Center Drive | J42: Rockville | K42: VA | L42: 23146 | M42: thin.v.pham@jci.com | N42: 98166 | O42: Security and Access Systems (Airport, Library, Hospitals, etc.) Rental or Lease | P42: EA | Q42: each
A43: EP2494448 | B43: Department of General Services | C43: 42719 | D43: Patch all holes and cracks spot prime as needed apply one finish coat rm.#'s are 303-303a -305-305-a 306-306a 310-310a 332-332a 322-322a | E43: 1 | F43: 4400 | G43: 153887562 | H43: EMPIRE PAINTING CORP | I43: 12600 Erika Hill Pl | J43: Midlothian | K43: VA | L43: 23112 | M43: Aristotelis6@comcast.net | N43: 91054 | O43: Painting, Maintenance and Repair Services (Including Caulking) | P43: EA | Q43: each
A44: EP2494449 | B44: Department of General Services | C44: 42719 | D44: Prep wall for dry erase paint apply one coat of primmer wait 24 hours to dry apply dry erase paint wait 24 hours apply clear coat wait one week before writing on it. | E44: 1 | F44: 1050 | G44: 153887562 | H44: EMPIRE PAINTING CORP | I44: 12600 Erika Hill Pl | J44: Midlothian | K44: VA | L44: 23112 | M44: Aristotelis6@comcast.net | N44: 91054 | O44: Painting, Maintenance and Repair Services (Including Caulking) | P44: EA | Q44: each
A45: EP2494450 | B45: Department of Corrections | C45: 42719 | D45: Broccoli | E45: 96 | F45: 8.5 | G45: 58413261 | H45: E A PARKER & SONS LLC | I45: 1647 Kings Highway | J45: Oak Grove | K45: VA | L45: 22443 | M45: jimmy@parkerfarms.net | N45: 39084 | O45: Vegetables, Fresh | P45: CT | Q45: carton
A46: EP2494451 | B46: Department of Corrections | C46: 42719 | D46: Acorn Squash | E46: 200 | F46: 6.19 | G46: 58413261 | H46: E A PARKER & SONS LLC | I46: 1647 Kings Highway | J46: Oak Grove | K46: VA | L46: 22443 | M46: jimmy@parkerfarms.net | N46: 39084 | O46: Vegetables, Fresh | P46: CT | Q46: carton
A47: EP2494451 | B47: Department of Corrections | C47: 42719 | D47: Broccoli | E47: 480 | F47: 9.25 | G47: 58413261 | H47: E A PARKER & SONS LLC | I47: 1647 Kings Highway | J47: Oak Grove | K47: VA | L47: 22443 | M47: jimmy@parkerfarms.net | N47: 39084 | O47: Vegetables, Fresh | P47: CT | Q47: carton
A48: PCO1992467-V2 | B48: Keen Mountain Correctional Center | C48: 42719 | D48: HEADLIGHT H4703 | E48: 0 | F48: 10.37 | G48: 83055087 | H48: KIDD TIRE AUTO PARTS | I48: 127 Walnut Street | J48: North Tazewell | K48: VA | L48: 24630 | M48: mkidd@kiddtire.com | N48: 5537 | O48: Headlights, Accessories and Parts (Including Lamps) | P48: EA | Q48: each
A49: PCO1995426 | B49: Keen Mountain Correctional Center | C49: 42719 | D49: ROUTINE CHECKUP AND HEARTWORK PILLS FOR ROMMEL AND TOTO - SERVICE ON 12/9/16 | E49: 1 | F49: 795.25 | G49: 123472524 | H49: SOUTHWEST VIRGINIA VETERINARY SERVICES | I49: 309 Overlook Drive | J49: Lebanon | K49: VA | L49: 24266 | M49: connect@svvspets.com | N49: 96206 | O49: Animal Care, Animal Health, Animal Shelter, Animal Production (Breeding), Animal Training Services, etc. (Including Pet Services, All Types) | P49: EA | Q49: each
A50: EP2576050-V2 | B50: Virginia Military Institute | C50: 42894 | D50: CK-Mini Yellow Chicks | E50: 0 | F50: 4.75 | G50: 89250799 | H50: K & M INTERNATIONAL | I50: 1955 Midway Drive | J50: Twinsburg | K50: OH | L50: 44087 | M50: csigler@kmtoys.com | N50: 3778 | O50: Souvenirs: Promotional, Advertising, etc. | P50: EA | Q50: each | R50: 12321
A51: PCO2087017-V2 | B51: Virginia Department of Health | C51: 42894 | D51: AME EAGLE OFF 8.5X14 30% 20# | E51: 0 | F51: 71.87 | G51: 195583778 | H51: THE SUPPLY ROOM COMPANIES | I51: PO BOX 1810 | J51: ASHLAND | K51: VA | L51: 23005 | M51: kmcintyre@tsrcinc.net | N51: 61600 | O51: OFFICE SUPPLIES, GENERAL, ENVIRONMENTALLY CERTIFIED BY AN AGENCY ACCEPTED CERTIFICATION ENTITY | P51: CT | Q51: carton | R51: AME31600502
A52: PCO1995127-V2 | B52: Piedmont VA Community College | C52: 42719 | D52: 60 X 24" Laminated Banner With PVCC Logo" | E52: 1 | F52: 45 | G52: 618959469 | H52: VIRGINIA CORRECTIONAL ENTERPRISES | I52: 5200 Commerce Road | J52: Richmond | K52: VA | L52: 23234 | M52: Maryanne.turner@vadoc.virginia.gov | N52: 35010 | O52: Banners, Pennants, and Decorative Fans, Drapes, and Pull Downs | P52: EA | Q52: each | R52: 0152 OD48 BNNR
A53: PCO1995127-V2 | B53: Piedmont VA Community College | C53: 42719 | D53: Shipping | E53: 1 | F53: 8 | G53: 618959469 | H53: VIRGINIA CORRECTIONAL ENTERPRISES | I53: 5200 Commerce Road | J53: Richmond | K53: VA | L53: 23234 | M53: Maryanne.turner@vadoc.virginia.gov | N53: 96286 | O53: Transportation of Goods and Other Freight Services | P53: EA | Q53: each | R53: ZMRV 152
A54: EP2493957 | B54: Virginia Commonwealth University | C54: 42719 | D54: Shipping | E54: 1 | F54: 38.66 | G54: 832499300 | H54: A B SCIEX LLC | I54: 1201 Radio Road Attn Accounts Payable | J54: Redwood City | K54: CA | L54: 94065 | M54: servicesales@absciex.com | N54: 19389 | O54: Test Kits and Supplies, Chemistry (Not Otherwise Classified) | P54: EA | Q54: each | R54: 10176167
A55: PCO1994962 | B55: Richard Bland College | C55: 42719 | D55: 15 Aleks 18 week math codes | E55: 15 | F55: 81 | G55: 1213206 | H55: MCGRAW-HILL GLOBAL EDUCATION LLC | I55: 8787 Orion Pl | J55: Columbus | K55: OH | L55: 43240-4027 | M55: bidsandcontracts@mheducation.com | N55: 92478 | O55: Teaching and Instruction Services (Including Elementary and Secondary Education, Higher Education and Adult Education) | P55: EA | Q55: each
A56: EP2494142 | B56: Department of Blind and Vision Impaired | C56: 42719 | D56: Interpreting services for Elizabeth Spiers on 10/01/16 | E56: 1 | F56: 190 | G56: 80157079 | H56: THOMPSON INTERPRETING LLC | I56: 11803 Kennedy Lane | J56: Fredericksburg | K56: VA | L56: 22407 | M56: shelly.thompson@verizon.net | N56: 96117 | O56: Interpreter Services - Electronically Assisted - Foreign Language, Hearing Impaired, etc., (See Item 46 For Interpreter Services - Not Electronically Assisted) | P56: EA | Q56: each
A57: DO1849775 | B57: College of William and Mary | C57: 42580 | D57: DellLeaseQuote ********* 586for1DellPrecisionTower36201styearofa4yearleaseAnnualleasepaymentof$36304peryearforQUANTITYOF1desktopTotalamountfinanced$133915Masterlease4163375 | E57: 1 | F57: 363.04 | G57: 801216433 | H57: DELL FINANCIAL SERVICES L P | I57: One Dell Way | J57: Round Rock | K57: TX | L57: 78682 | M57: David_B_Bailey@Dell.com | N57: 20453 | O57: Microcomputers, Desktop or Tower based | P57: EA | Q57: each
A58: A208_P3044078 | B58: Virginia Polytechnic Institute and State Universit | C58: 42566 | D58: 419036-BIC Wite-Out Brand Quick-Dry Correction Flu | E58: 1 | F58: 16.03 | G58: 562074389 | H58: GUY BROWN PRODUCTS | I58: 320 Seven Springs Way Ste 450 | J58: Brentwood | K58: TN | L58: 37027 | N58: 61600 | O58: OFFICE SUPPLIES, GENERAL, ENVIRONMENTALLY CERTIFIED BY AN AGENCY ACCEPTED CERTIFICATION ENTITY | P58: DZN | Q58: dozen
A59: A208_P3044078 | B59: Virginia Polytechnic Institute and State Universit | C59: 42566 | D59: 889862-Brother Toner Cartridge, TN-315, High Yield | E59: 3 | F59: 78.38 | G59: 562074389 | H59: GUY BROWN PRODUCTS | I59: 320 Seven Springs Way Ste 450 | J59: Brentwood | K59: TN | L59: 37027 | N59: 61600 | O59: OFFICE SUPPLIES, GENERAL, ENVIRONMENTALLY CERTIFIED BY AN AGENCY ACCEPTED CERTIFICATION ENTITY | P59: EA | Q59: each
A60: A208_P3044085 | B60: Virginia Polytechnic Institute and State Universit | C60: 42566 | D60: BSN 42051-Business Source File Storage Box - 12 x | E60: 1 | F60: 23.95 | G60: 23887540 | H60: TAYLOR OFFICE SUPPLY INC | I60: PO Box 1228 | J60: Radford | K60: VA | L60: 24143 | N60: 61600 | O60: OFFICE SUPPLIES, GENERAL, ENVIRONMENTALLY CERTIFIED BY AN AGENCY ACCEPTED CERTIFICATION ENTITY | P60: EA | Q60: each
A61: A208_P3044094 | B61: Virginia Polytechnic Institute and State Universit | C61: 42566 | D61: EMBL2-0000-embroidery 2 lines per coat | E61: 5 | F61: 6 | G61: DB5006205 | H61: CHEF WORKS INC | I61: 12325 Kerran St | J61: Poway | K61: CA | L61: 92064 | N61: 20100 | O61: CLOTHING ACCESSORIES (SEE CLASS 800 FOR SHOES AND BOOTS) | P61: EA | Q61: each
A62: A208_P3044094 | B62: Virginia Polytechnic Institute and State Universit | C62: 42566 | D62: EMBL-0000-PTC Logo | E62: 5 | F62: 4 | G62: DB5006205 | H62: CHEF WORKS INC | I62: 12325 Kerran St | J62: Poway | K62: CA | L62: 92064 | N62: 20100 | O62: CLOTHING ACCESSORIES (SEE CLASS 800 FOR SHOES AND BOOTS) | P62: EA | Q62: each
A63: A208_P3044094 | B63: Virginia Polytechnic Institute and State Universit | C63: 42566 | D63: PKWC-WHT-2XL-Bordeaux Chef coat white long sleeve | E63: 2 | F63: 16.27 | G63: DB5006205 | H63: CHEF WORKS INC | I63: 12325 Kerran St | J63: Poway | K63: CA | L63: 92064 | N63: 20100 | O63: CLOTHING ACCESSORIES (SEE CLASS 800 FOR SHOES AND BOOTS) | P63: EA | Q63: each
A64: A208_P3044094 | B64: Virginia Polytechnic Institute and State Universit | C64: 42566 | D64: KNSS-WHT-L-Tivoli Chef coat white short sleeve wit | E64: 2 | F64: 13.72 | G64: DB5006205 | H64: CHEF WORKS INC | I64: 12325 Kerran St | J64: Poway | K64: CA | L64: 92064 | N64: 20100 | O64: CLOTHING ACCESSORIES (SEE CLASS 800 FOR SHOES AND BOOTS) | P64: EA | Q64: each
A65: A208_P3044094 | B65: Virginia Polytechnic Institute and State Universit | C65: 42566 | D65: KNSS-WHT-2XL-Tivoli Chef coat white short sleeve w | E65: 1 | F65: 15.72 | G65: DB5006205 | H65: CHEF WORKS INC | I65: 12325 Kerran St | J65: Poway | K65: CA | L65: 92064 | N65: 20100 | O65: CLOTHING ACCESSORIES (SEE CLASS 800 FOR SHOES AND BOOTS) | P65: EA | Q65: each
A66: A208_P3044099 | B66: Virginia Polytechnic Institute and State Universit | C66: 42566 | D66: 4464K97-Type 304 Stainless STL Threaded Pipe Fitti | E66: 3 | F66: 17.47 | G66: 606774891 | H66: MCMASTER CARR SUPPLY COMPANY | I66: PO Box 740100 | J66: Atlanta | K66: GA | L66: 30374-0100 | N66: 49535 | O66: Cabinets and Cases, Storage (For Slides and Specimens) | P66: EA | Q66: each
A67: A208_P3044104 | B67: Virginia Polytechnic Institute and State Universit | C67: 42566 | D67: Confirming Invoice for Balance Maintenance | E67: 41 | F67: 60 | G67: 626982920 | H67: CARLTON GROUP INC | I67: 196 Industrial Dr | J67: Roanoke | K67: VA | L67: 24019-8506 | N67: 93856 | O67: Hospital and Medical Equipment, General, Maintenance and Repair | P67: EA | Q67: each
A68: A208_P3044110 | B68: Virginia Polytechnic Institute and State Universit | C68: 42566 | D68: DYM 30327-Dymo Filing Label - 0.56 Width x 3.43"" | E68: 1 | F68: 9.2 | G68: 23887540 | H68: TAYLOR OFFICE SUPPLY INC | I68: PO Box 1228 | J68: Radford | K68: VA | L68: 24143 | N68: 61600 | O68: OFFICE SUPPLIES, GENERAL, ENVIRONMENTALLY CERTIFIED BY AN AGENCY ACCEPTED CERTIFICATION ENTITY | P68: BX | Q68: box
B71: Sample Data Which Reconciles
B72: Payment Record, 1st Quarter 2003
B73: AGY_AGENCY_KEY | C73: FNDDTL_FUND_DETAIL_KEY | D73: OBJ_OBJECT_KEY | E73: SPRG_SUB_PROGRAM_KEY | F73: VENDOR_NAME | G73: AMOUNT | J73: AGY_AGENCY_CODE | K73: AGY_AGENCY_KEY | L73: AGY_AGENCY_NAME
B74: 107 | C74: 432 | D74: 329 | E74: 2697 | F74: VICTOR PRODUCTS CORP | G74: 249.5 | J74: 146 | K74: 107 | L74: The Science Museum of Virginia
B76: PO Data
A77: PONUMBER | B77: AGENCY | C77: ORDEREDDATE | D77: VENDORCOMMODITYDESC | E77: QUANTITYORDERED | F77: PRICE | G77: VENDORID | H77: VENDORNAME | I77: VENDORADDRESS | J77: VENDORCITY | K77: VENDORSTATE | L77: VENDORPOSTALCODE | M77: VENDORLOC_EMAILADDRESS | N77: NIGPCODE | O77: NIGPDESCRIPTION | P77: UOMCode | Q77: UOMDesc | R77: VENDORPARTNUMBER | S77: MANPARTNUMBER
A78: DO60246 | B78: Science Museum of Virginia | C78: 37656 | D78: Popcorn - 24/16oz pkgs | E78: 10 | F78: 24.95 | G78: 999999999999 | H78: Victor Products | N78: 74085 | O78: Vending Machines, Refrigerated | P78: EA | Q78: each
F80: =F78*E78 -> 249.5

Sheet VA to UnivJE
F2: Mapping | K2: Sample Transformed Expense Data
A3: Universal Journal | F3: Expense | G3: Expense | H3: Revenue | I3: Revenue | K3: 1Q 2003 | L3: 1Q 2003 | M3: 1Q 2003 | N3: 1Q 2003 | O3: 1Q 2014 | P3: 1Q 2014 | Q3: 1Q 2014 | R3: 1Q 2014 | U3: Sample Input Data | W3: 1Q 2003 | X3: 1Q 2003 | Y3: 1Q 2003 | Z3: 1Q 2003 | AA3: Sample Input Data | AB3: 1Q 2014 | AC3: 1Q 2014 | AD3: 1Q 2014 | AE3: 1Q 2014
A4: Field Contents | B4: fFieldName | D4: Field Type | E4: Data Source | F4: 2003-2012 | G4: 2012 + | H4: 2003-2012 | I4: 2012 + | K4: Rec 1 | L4: Rec 2 | M4: Rec 3 | N4: Rec 4 | O4: Rec 1 | P4: Rec 2 | Q4: Rec 3 | R4: Rec 4 | U4: Input Field Order '03-'13 | W4: Rec 1 | X4: Rec 2 | Y4: Rec 3 | Z4: Rec 4 | AA4: Input Field Order '14-'16 | AB4: Rec 1 | AC4: Rec 2 | AD4: Rec 3 | AE4: Rec 4
A5: Instrument ID | B5: instID | C5: Unique ID | D5: Number | E5: Unique Instrument ID
A6: Business Event / Journal ID | B6: jrnlID | C6: Unique ID | D6: Number | E6: Fiscal Date File count + Record count
A7: Jrnl Line No | B7: jrnlLineID | C7: Unique ID | D7: Number | E7: Increment
A8: Journal / Event Description | B8: jrnlDescript | C8: Input Field | D8: Text | E8: Mapped Field From File | F8: VENDOR_NAME | G8: VENDOR_NAME | H8: AGY_AGENCY_KEY | I8: AGY_AGENCY_KEY | K8: BLACKWELLS BOOK SERVICES | L8: BLACKWELLS BOOK SERVICES | M8: BLACKWELLS BOOK SERVICES | N8: BLACKWELLS BOOK SERVICES | O8: AGENCY TRANSACTION VOUCHER | P8: AGENCY TRANSACTION VOUCHER | Q8: COYNE TEXTILE SERVICES | R8: COYNE TEXTILE SERVICES | T8: 5
A9: Ledger | B9: ledgerID | C9: Constant | D9: Text | E9: Actual-Historical
A10: Jrnl Type | B10: jrnlType | C10: Constant | D10: Text | E10: Financial
A11: Book-code / Basis | B11: bookCodeID | C11: Constant | D11: Text | E11: Shared-3rd-Party
A12: Legal Entity (CO. / Owner) | B12: legalEntityID | C12: Xref Key | D12: Number | E12: Mapped Field From File | F12: AGENCY | G12: AGENCY | H12: AGY_AGENCY_KEY | I12: AGY_AGENCY_KEY | J12: 1 | K12: 267 | L12: 267 | M12: 267 | N12: 267 | O12: 210 | P12: 210 | Q12: 210 | R12: 210 | T12: 1 | U12: AGY_AGENCY_KEY | V12: 1 | W12: 267 | X12: 267 | Y12: 267 | Z12: 267 | AA12: AGY_AGENCY_KEY | AB12: 210 | AC12: 210 | AD12: 210 | AE12: 210
A13: Center ID | B13: centerID | C13: Xref Key | D13: Number | E13: Mapped Field From File | F13: FUND | G13: FUND | H13: FNDDTL_FUND_DETAIL_KEY | I13: FNDDTL_FUND_DETAIL_KEY | J13: 2 | K13: 1552 | L13: 1552 | M13: 1552 | N13: 1552 | O13: 1401 | P13: 1401 | Q13: 1401 | R13: 1401 | T13: 2 | U13: FNDDTL_FUND_DETAIL_KEY | V13: 2 | W13: 1552 | X13: 1552 | Y13: 1552 | Z13: 1552 | AA13: AMOUNT | AB13: 61.36 | AC13: 61.36 | AD13: 19.61 | AE13: 19.61
A14: Project ID | B14: projectID | C14: Xref Key | D14: Number | E14: Mapped Field From File | F14: PROGRAM | G14: PROGRAM | K14: 2701 | L14: 2701 | M14: 2701 | N14: 2701 | O14: 4172 | P14: 4172 | Q14: 4172 | R14: 4172 | T14: 4 | U14: OBJ_OBJECT_KEY | V14: 3 | W14: 56 | X14: 56 | Y14: 56 | Z14: 56 | AA14: FNDDTL_FUND_DETAIL_KEY | AB14: 1401 | AC14: 1401 | AD14: 1401 | AE14: 1401
A15: Product / Material ID | B15: productID | C15: Constant | D15: Text
A16: Nominal Account | B16: accountID | C16: Xref Key | D16: Number | E16: Mapped Field From File | F16: OBJECT | G16: OBJECT | H16: SOURCE | I16: SOURCE | J16: 3 | K16: 56 | L16: 56 | M16: 56 | N16: 56 | O16: 268 | P16: 268 | Q16: 268 | R16: 268 | T16: 3 | U16: SPRG_SUB_PROGRAM_KEY | V16: 4 | W16: 2701 | X16: 2701 | Y16: 2701 | Z16: 2701 | AA16: OBJ_OBJECT_KEY | AB16: 268 | AC16: 268 | AD16: 268 | AE16: 268
A17: Curr. Code Source | B17: currencyCodeSourceID | C17: Constant | D17: Text | E17: USD | U17: VENDOR_NAME | V17: 5 | W17: BLACKWELLS BOOK SERVICES | X17: BLACKWELLS BOOK SERVICES | Y17: BLACKWELLS BOOK SERVICES | Z17: BLACKWELLS BOOK SERVICES | AA17: SPRG_SUB_PROGRAM_KEY | AB17: 4172 | AC17: 4172 | AD17: 4172 | AE17: 4172
A18: Currency Type Code Source | B18: currencyTypeCodeSourceID | C18: Constant | D18: Text | E18: TXN | U18: AMOUNT | V18: 6 | W18: 271.93 | X18: 289.74 | Y18: 73.77 | Z18: 366.3 | AA18: VENDOR_NAME | AB18: AGENCY TRANSACTION VOUCHER | AC18: AGENCY TRANSACTION VOUCHER | AD18: COYNE TEXTILE SERVICES | AE18: COYNE TEXTILE SERVICES
A19: Curr. Code Target | B19: currencyCodeTargetID | C19: Constant | D19: Text | E19: USD | AA19: VOUCHER_DATE | AB19: 41500 | AC19: 41472 | AD19: 41541 | AE19: 41533
A20: Currency Type Code Target | B20: currencyTypeCodeTargetID | C20: Constant | D20: Text | E20: BASE-LE
A21: Transaction Amount | B21: transAmount | C21: Value | D21: Number | E21: Mapped Field From File | F21: AMOUNT | G21: AMOUNT | H21: AMOUNT | I21: AMOUNT | J21: 4 | K21: 271.93 | L21: 289.74 | M21: 73.77 | N21: 366.3 | O21: 61.36 | P21: 61.36 | Q21: 19.61 | R21: 19.61 | T21: 6
A22: Fiscal Period | B22: fiscalPeriod | C22: Derived | D22: Date | E22: Date from File Name | F22: File Date | G22: File Date | H22: File Date | I22: File Date | T22: 1
A23: Acctg. Date | B23: acctDate | C23: Derived | D23: Date | E23: Date from File or File Name | F23: File Date | G23: VOUCHER_DATE | H23: File Date | I23: DEPOSIT DT | K23: 2003 | O23: 41500 | P23: 41472 | Q23: 41541 | R23: 41533 | T23: 2 | U23: Fiscal Date (consntat from file)
A24: Transaction Date | B24: transDate | C24: Input Field | D24: Date | E24: Mapped Field From File | F24: File Date | G24: VOUCHER_DATE | H24: File Date | I24: DEPOSIT DT | K24: 2003 | O24: 41500 | P24: 41472 | Q24: 41541 | R24: 41533 | T24: 2 | U24: Accounting Date (constant from file)
A25: Direct vs. Offset Flag | B25: dirVsOffsetFlg | C25: Constant | D25: Flag | E25: Y/N based upon record
A26: Reconciliable Flag | B26: reconcileFlg | C26: Constant | D26: Flag | E26: N
A27: Adjustment Flag | B27: adjustFlg | C27: Constant | D27: Flag | E27: N
A28: Movement Flag | B28: movementFlg | C28: Constant | D28: Flag | E28: N
A29: Unit of Measure | B29: unitOfMeasure | C29: Constant | D29: Text | E29: Financial
A30: Statistical Amount | B30: statisticAmount | C30: Constant | D30: Number | E30: 0
A31: Audit Trial Extension ID | B31: extensionIDAuditTrail | C31: Xref Key | D31: Number | E31: default 0, not currently used
A32: Source Extension ID | B32: extensionIDSource | C32: Xref Key | D32: Number | E32: default 0, not currently used
A33: Classification Extension ID | B33: extensionIDClass | C33: Xref Key | D33: Number | E33: default 0, not currently used
A34: Date Extension ID | B34: extensionIDDates | C34: Xref Key | D34: Number | E34: default 0, not currently used
A35: Other Customization Ext ID | B35: extensionIDCustom | C35: Xref Key | D35: Number | E35: default 0, not currently used
C37: instID | D37: jrnlID | E37: jrnlLineID | F37: jrnlDescript | G37: ledgerID | H37: jrnlType | I37: bookCodeID | J37: legalEntityID | K37: centerID | L37: projectID | M37: productID | N37: accountID | O37: currencyCodeSourceID | P37: currencyTypeCodeSourceID | Q37: currencyCodeTargetID | R37: currencyTypeCodeTargetID | S37: transAmount | T37: fiscalPeriod | U37: acctDate | V37: transDate | W37: dirVsOffsetFlg | X37: reconcileFlg | Y37: adjustFlg | Z37: movementFlg | AA37: unitOfMeasure | AB37: statisticAmount | AC37: extensionIDAuditTrail | AD37: extensionIDSource | AE37: extensionIDClass | AF37: extensionIDDates | AG37: extensionIDCustom
B38: Potential Default Values | C38: "0", | D38: "0", | E38: "1", | F38: " ", | G38: "ACTUALS" | H38: "FIN" | I38: "SHRD-3RD-PARTY" | J38: "0" | K38: "0" | L38: "0" | M38: "0" | N38: "0" | O38: "USD", | P38: "TXN", | Q38: "USD", | R38: "BASE-LE" | S38: "0", | T38: "0", | U38: "0", | V38: "0", | W38: "D", | X38: "Y", | Y38: "N", | Z38: "N", | AA38: "", | AB38: "", | AC38: "", | AD38: "", | AE38: "", | AF38: "", | AG38: "",

Sheet Universial Journal Data Mod

Sheet New Unv Data Model
A1: Common on All Bus. Process | L1: Common on All Bus. Process | X1: Unique by Business Process | AF1: Unique by Business Process | AI1: Unique by Business Process
A2: Universal Journal | L2: Universal Balance | X2: Universal Header | AF2: Commitment | AI2: Contract | AL2: Invovled Party | AS2: Trading Partners
A3: Field Contents | B3: Field Name | C3: Field Content | D3: Field Format | E3: Length | F3: PO Example Field | G3: FieldName | I3: Field Type | J3: Data Source | L3: Field Contents | M3: Field Name | N3: Field Content | O3: Field Format | P3: Length | Q3: PO Example Field | R3: Inv. Example | S3: FieldName | U3: Field Type | V3: Data Source | X3: Field Contents | Y3: PO Example Field | Z3: Inv. Example | AA3: FieldName | AC3: Field Type | AD3: Data Source | AF3: Field Contents | AG3: PO Example Field | AI3: Field Contents | AJ3: PO Example Field | AL3: Field Contents | AM3: Field Name | AN3: Field Content | AO3: Field Format | AP3: Length | AQ3: PO Example Field | AS3: Field Contents
A4: Involved Party ID | E4: 15 | F4: VENDORID | L4: Involved Party ID | Q4: VENDORID | X4: Involved Party ID | Y4: VENDORID | AF4: Involved Party ID | AG4: VENDORID | AI4: Involved Party ID | AJ4: VENDORID | AL4: Involved Party ID | AN4: Based on Vendor ID | AQ4: VENDORID | AS4: Involved Party ID
A5: Contract ID | G5: instID | H5: Unique ID | I5: Number | J5: Unique Instrument ID | L5: Contract ID | S5: instID | T5: Unique ID | U5: Number | V5: Unique Instrument ID | X5: Contract ID | AF5: Contract ID | AI5: Contract ID | AS5: Related IP IDs
A6: Commitment ID | L6: Commitment ID | X6: Commitment ID | AF6: Commitment ID
L7: Balance ID | Q7: PONUMBER | R7: NIGPCODE | S7: balID | T7: Unique ID | U7: Number | V7: File count + Record count | X7: Balance ID/Business Event ID | Y7: PONUMBER | Z7: NIGPCODE
A8: Instrument ID | B8: instID | C8: Unique ID | D8: Number | E8: 50 | F8: based on PO Num | G8: jrnlID | H8: Unique ID | I8: Number | J8: Fiscal Date File count + Record count | AM8: ipName | AN8: Value | AO8: Text | AP8: 128 | AQ8: VENDORNAME
A9: Business Event / Journal ID | B9: jrnlID | C9: Unique ID | D9: Number | G9: jrnlLineID | H9: Unique ID | I9: Number | J9: Increment | Y9: ORDEREDDATE | AM9: ipAddress | AN9: Value | AO9: Text | AP9: 255 | AQ9: VENDORADDRESS
A10: Jrnl Line No | B10: jrnlLineID | C10: Unique ID | D10: Number | AM10: ipCity | AN10: Value | AO10: Text | AP10: 255 | AQ10: VENDORCITY
A11: Business Event Code | B11: busEventCD | C11: Constant | D11: Text | E11: 16 | G11: jrnlDescript | H11: Input Field | I11: Text | J11: Mapped Field From File | AM11: ipState | AN11: Value | AO11: Text | AP11: 50 | AQ11: VENDORSTATE
A12: Source System ID | B12: sourceID | C12: Constant | D12: Text | E12: 16 | G12: ledgerID | H12: Constant | I12: Text | J12: Actual-Historical | S12: ledgerID | T12: Constant | U12: Text | V12: Actual-Historical | AM12: ipCountry | AN12: Constant | AO12: Text | AP12: 255
A13: Original Process ID | B13: processID | C13: Constant | D13: Text | E13: 16 | G13: jrnlType | H13: Constant | I13: Text | J13: Financial | S13: jrnlType | T13: Constant | U13: Text | V13: Financial, FINADJ | AM13: ipPostalCode | AN13: Value | AO13: Text | AP13: 255 | AQ13: VENDORPOSTALCODE
A14: Original Document ID | B14: originalDocID | E14: 50 | F14: PONUMBER | G14: bookCodeID | H14: Constant | I14: Text | J14: Shared-3rd-Party | S14: bookCodeID | T14: Constant | U14: Text | V14: Shared-3rd-Party | AM14: ipEmail | AN14: Value | AO14: Text | AP14: 100 | AQ14: VENDORLOC_EMAILADDRESS
A15: Journal / Event Description | B15: jrnlDescript | C15: Input Field | D15: Text | E15: 2000 | F15: AGENCY | G15: legalEntityID | H15: Xref Key | I15: Number | J15: Mapped Field From File | S15: legalEntityID | T15: Xref Key | U15: Number | V15: Mapped Field From File | AM15: ipVendorID | AN15: Value | AO15: Test | AP15: 15 | AQ15: VENDORID
A16: Ledger | B16: ledgerID | C16: Constant | D16: Text | E16: 16 | G16: centerID | H16: Xref Key | I16: Number | J16: Mapped Field From File | L16: Ledger | M16: ledgerID | N16: Constant | O16: Text | P16: 16 | S16: centerID | T16: Xref Key | U16: Number | V16: Mapped Field From File
A17: Jrnl Type | B17: jrnlType | C17: Constant | D17: Text | E17: 16 | G17: projectID | H17: Xref Key | I17: Number | J17: Mapped Field From File | L17: Jrnl Type | M17: jrnlType | N17: Constant | O17: Text | P17: 16 | S17: projectID | T17: Xref Key | U17: Number | V17: Mapped Field From File
A18: Book-code / Basis | B18: bookCodeID | C18: Constant | D18: Text | E18: 16 | G18: productID | H18: Constant | I18: Text | L18: Book-code / Basis | M18: bookCodeID | N18: Constant | O18: Text | P18: 16 | S18: productID | T18: Constant | U18: Text
A19: Legal Entity (CO. / Owner) | B19: legalEntityID | C19: Xref Key | D19: Number | G19: accountID | H19: Xref Key | I19: Number | J19: Mapped Field From File | L19: Legal Entity (CO. / Owner) | M19: legalEntityID | N19: Xref Key | O19: Number | Q19: AGENCY | S19: accountID | T19: Xref Key | U19: Number | V19: Mapped Field From File | AM19: Add Instrument Type
A20: Center ID | B20: centerID | C20: Xref Key | D20: Number | G20: currencyCodeSourceID | H20: Constant | I20: Text | J20: USD | L20: Center ID | M20: centerID | N20: Xref Key | O20: Number | S20: currencyCodeSourceID | T20: Constant | U20: Text | V20: USD | AM20: Add Effective Date Fields.
A21: Project ID | B21: projectID | C21: Xref Key | D21: Number | G21: currencyTypeCodeSourceID | H21: Constant | I21: Text | J21: TXN | L21: Project ID | M21: projectID | N21: Xref Key | O21: Number | S21: currencyTypeCodeSourceID | T21: Constant | U21: Text | V21: TXN | AF21: HSBC has an Insurance Claim, and a Trading Arrangement at this level
A22: Product / Material ID | B22: productID | C22: Constant | D22: Number | G22: currencyCodeTargetID | H22: Constant | I22: Text | J22: USD | L22: Product / Material ID | M22: productID | N22: Constant | O22: Number | S22: currencyCodeTargetID | T22: Constant | U22: Text | V22: USD
A23: Nominal Account | B23: accountID | C23: Xref Key | D23: Number | G23: currencyTypeCodeTargetID | H23: Constant | I23: Text | J23: BASE-LE | L23: Nominal Account | M23: accountID | N23: Xref Key | O23: Number | S23: currencyTypeCodeTargetID | T23: Constant | U23: Text | V23: BASE-LE
A24: Alternate Account Code | B24: altAccountID | C24: Constant | D24: Number | G24: transAmount | H24: Value | I24: Number | J24: Mapped Field From File | L24: Alternate Account Code | M24: altAccountID | N24: Constant | O24: Number | S24: fiscalYear | T24: Derived | U24: Date | V24: Year from Fiscal Date
A25: Curr. Code Source | B25: currencyCodeSourceID | C25: Constant | D25: Text | E25: 16 | G25: fiscalPeriod | H25: Derived | I25: Date | J25: Date from File Name | L25: Curr. Code Source | M25: currencyCodeSourceID | N25: Constant | O25: Text | P25: 16 | S25: transAmount | T25: Value | U25: Number | V25: Mapped Field From File
A26: Currency Type Code Source | B26: currencyTypeCodeSourceID | C26: Constant | D26: Text | E26: 16 | G26: acctDate | H26: Derived | I26: Date | J26: Date from File or File Name | L26: Currency Type Code Source | M26: currencyTypeCodeSourceID | N26: Constant | O26: Text | P26: 16 | X26: HSBC has a chedule construct, but it's an independent hiearchy, not related to balances and trasnactions. Interesting. Go back to REA book to review.
A27: Curr. Code Target | B27: currencyCodeTargetID | C27: Constant | D27: Text | E27: 16 | G27: transDate | H27: Input Field | I27: Date | J27: Mapped Field From File | L27: Curr. Code Target | M27: currencyCodeTargetID | N27: Constant | O27: Text | P27: 16 | X27: I wonder if the header could be used for this concept in some way
A28: Currency Type Code Target | B28: currencyTypeCodeTargetID | C28: Constant | D28: Text | E28: 16 | G28: dirVsOffsetFlg | H28: Constant | I28: Flag | J28: Y/N based upon record | L28: Currency Type Code Target | M28: currencyTypeCodeTargetID | N28: Constant | O28: Text | P28: 16
A29: Fiscal Period | B29: fiscalPeriod | C29: Derived | D29: Date | G29: adjustFlg | H29: Constant | I29: Flag | J29: N | L29: Fiscal Year | M29: fiscalYear | N29: Derived | O29: Date
A30: Acctg. Date | B30: acctDate | C30: Derived | D30: Date | G30: movementFlg | H30: Constant | I30: Flag | J30: N
A31: Transaction Date | B31: transDate | C31: Input Field | D31: Date | F31: ORDEREDDATE | G31: unitOfMeasure | H31: Constant | I31: Text | J31: Financial | S31: movementFlg | T31: Constant | U31: Flag | V31: N
A32: Movement Flag | B32: movementFlg | C32: Constant | D32: Flag | E32: 1 | G32: statisticAmount | H32: Constant | I32: Number | J32: 0 | L32: Movement Flag | M32: movementFlg | N32: Constant | O32: Flag | P32: 1 | S32: unitOfMeasure | T32: Constant | U32: Text | V32: Financial
A33: Direct vs. Offset Flag | B33: dirVsOffsetFlg | C33: Constant | D33: Flag | E33: 1 | G33: statisticAmount | H33: Constant | I33: Number | J33: 0 | L33: Direct vs. Offset Flag | M33: dirVsOffsetFlg | N33: Constant | O33: Flag | P33: 1
A34: Reconciliable Flag | B34: reconcileFlg | C34: Constant | D34: Flag | E34: 1 | G34: extensionIDAuditTrail | H34: Xref Key | I34: Number | J34: default 0, not currently used | L34: Reconciliable Flag | M34: reconcileFlg | N34: Constant | O34: Flag | P34: 1 | S34: statisticAmount | T34: Constant | U34: Number | V34: 0
A35: Adjustment Flag | B35: adjustFlg | C35: Constant | D35: Flag | E35: 1 | L35: Adjustment Flag | M35: adjustFlg | N35: Constant | O35: Flag | P35: 1 | X35: Audit Trial Extension ID | AA35: extensionIDAuditTrail | AB35: Xref Key | AC35: Number | AD35: default 0, not currently used
A36: Unit of Measure | B36: unitOfMeasure | C36: Constant | D36: Text | E36: 50 | F36: UNITOFMEASURECODE | G36: extensionIDClass | H36: Xref Key | I36: Number | J36: default 0, not currently used | L36: Unit of Measure | M36: unitOfMeasure | N36: Constant | O36: Text | P36: 50 | X36: Source Extension ID | AA36: extensionIDSource | AB36: Xref Key | AC36: Number | AD36: default 0, not currently used
A37: Uniit Price | B37: unitPrice | C37: Value | D37: Number | F37: PRICE | G37: extensionIDDates | H37: Xref Key | I37: Number | J37: default 0, not currently used | X37: Classification Extension ID | AA37: extensionIDClass | AB37: Xref Key | AC37: Number | AD37: default 0, not currently used
A38: Transaction Amount | B38: transAmount | C38: Value | D38: Number | L38: Transaction Amount - Per01 | M38: transAmountPer01 | N38: Value | O38: Number | X38: Date Extension ID | AA38: extensionIDDates | AB38: Xref Key | AC38: Number | AD38: default 0, not currently used
A39: Statistical Amount | B39: statisticAmount | C39: Value | D39: Number | F39: QUANTITYORDERED | L39: Transaction Amount - Per02 | M39: transAmountPer02 | N39: Value | O39: Number | X39: Other Customization Ext ID | AA39: extensionIDCustom | AB39: Xref Key | AC39: Number | AD39: default 0, not currently used
A40: Rule Set ID | B40: ruleSetID | C40: Constant | D40: Text | E40: 16 | L40: Transaction Amount - Per03 | M40: transAmountPer03 | N40: Value | O40: Number
A41: Rule ID | B41: ruleID | C41: Constant | D41: Text | E41: 16 | L41: Transaction Amount - Per04 | M41: transAmountPer04 | N41: Value | O41: Number
A42: Audit Trial Extension ID | B42: extensionIDAuditTrail | C42: Xref Key | D42: Number | L42: Transaction Amount - Per05 | M42: transAmountPer05 | N42: Value | O42: Number
A43: Source Extension ID | B43: extensionIDSource | C43: Xref Key | D43: Number | L43: Transaction Amount - Per06 | M43: transAmountPer06 | N43: Value | O43: Number
A44: Classification Extension ID | B44: extensionIDClass | C44: Xref Key | D44: Number | L44: Transaction Amount - Per07 | M44: transAmountPer07 | N44: Value | O44: Number
A45: Date Extension ID | B45: extensionIDDates | C45: Xref Key | D45: Number | L45: Transaction Amount - Per08 | M45: transAmountPer08 | N45: Value | O45: Number
A46: Other Customization Ext ID | B46: extensionIDCustom | C46: Xref Key | D46: Number | L46: Transaction Amount - Per09 | M46: transAmountPer09 | N46: Value | O46: Number
L47: Transaction Amount - Per10 | M47: transAmountPer10 | N47: Value | O47: Number
B48: These fields have been moved to the Extension Below…. | E48: 500 | F48: NIGPDESCRIPTION | L48: Transaction Amount - Per11 | M48: transAmountPer11 | N48: Value | O48: Number
E49: 2000 | F49: VENDORCOMMODITYDESC | L49: Transaction Amount - Per12 | M49: transAmountPer12 | N49: Value | O49: Number
E50: 255 | F50: VENDORPARTNUMBER | L50: Transaction Amount - Per13 | M50: transAmountPer13 | N50: Value | O50: Number
E51: 255 | F51: MANPARTNUMBER
E52: 128 | F52: UNITOFMEASUREDESC
E53: 12 | F53: NIGPCODE
A56: Spot | L56: Divide the key from the pads
L58: Make new Statistic pads (Daily and Monthly)
L59: HSBC has an accmulated balance for average calcs set of buckets
L63: Statistical Amount - Per13 | M63: statisticAmount13 | N63: Value | O63: Number
L65: Running Annual Balances?
A66: Universal Journal Extension
A67: Original PO Transaction
A68: Field Contents | B68: Field Name | C68: Field Content | D68: Field Format | E68: Length | F68: PO Example Field
A69: Involved Party ID | E69: 15 | F69: VENDORID
A70: Contract ID
A71: Commitment ID
A72: Instrument ID | B72: instID | C72: Unique ID | D72: Number | E72: 50 | F72: based on PO Num
A73: Business Event / Journal ID | B73: jrnlID | C73: Unique ID | D73: Number
A74: Jrnl Line No | B74: jrnlLineID | C74: Unique ID | D74: Number
A75: Order # | B75: PONUMBER | D75: VARCHAR2 | E75: 50
A76: Agency/Entity Description | B76: AGENCY | D76: VARCHAR2 | E76: 128
A77: Order Date | B77: ORDEREDDATE | C77: MM/DD/YYYY | D77: Date
A78: Item Description | B78: VENDORCOMMODITYDESC | D78: VARCHAR2 | E78: 2000
A79: Quantity Ordered | B79: QUANTITYORDERED | D79: NUMBER
A80: Unit Price | B80: PRICE | D80: NUMBER
A81: Vendor DUNS # | B81: VENDORID | D81: VARCHAR2 | E81: 15
A82: Vendor Name (as shown on order) | B82: VENDORNAME | D82: VARCHAR2 | E82: 128
A83: Order Street | B83: VENDORADDRESS | D83: VARCHAR2 | E83: 255
A84: Order City | B84: VENDORCITY | D84: VARCHAR2 | E84: 255
A85: Order State | B85: VENDORSTATE | D85: VARCHAR2 | E85: 50
A86: Order Zip Code | B86: VENDORPOSTALCODE | D86: VARCHAR2 | E86: 255
A87: Order eMail Contact | B87: VENDORLOC_EMAILADDRESS | D87: VARCHAR2 | E87: 100
A88: NIGP Code | B88: NIGPCODE | D88: VARCHAR2 | E88: 12
A89: NIGP Class Code Description | B89: NIGPDESCRIPTION | D89: VARCHAR2 | E89: 500
A90: Unit of Measure (UOM) | B90: UNITOFMEASURECODE | D90: VARCHAR2 | E90: 50
A91: UOM Description | B91: UNITOFMEASUREDESC | D91: VARCHAR2 | E91: 128
A92: Vendor Part # | B92: VENDORPARTNUMBER | D92: VARCHAR2 | E92: 255
A93: Manufacturer Part # | B93: MANPARTNUMBER | D93: VARCHAR2 | E93: 255
A96: Original Payment Tran
A97: Field Contents | B97: Field Name | C97: Field Content | D97: Field Format | E97: Length | F97: PO Example Field
A98: Involved Party ID | E98: 15 | F98: VENDORID
A99: Contract ID
A100: Commitment ID
A101: Instrument ID | B101: instID | C101: Unique ID | D101: Number | E101: 50 | F101: based on PO Num
A102: Business Event / Journal ID | B102: jrnlID | C102: Unique ID | D102: Number
A103: Jrnl Line No | B103: jrnlLineID | C103: Unique ID | D103: Number
B104: AGY_AGENCY_KEY | D104: VARCHAR2 | E104: 128 | F104: assumed sizes from above
B105: FNDDTL_FUND_DETAIL_KEY | D105: VARCHAR2 | E105: 128
B106: OBJ_OBJECT_KEY | D106: VARCHAR2 | E106: 128
B107: SPRG_SUB_PROGRAM_KEY | D107: VARCHAR2 | E107: 128
B108: VENDOR_NAME | D108: VARCHAR2 | E108: 128
B109: AMOUNT | D109: NUMBER | L109: Statistical Amount - Per01 | M109: statisticAmount01 | N109: Value | O109: Number
...

Sheet Univ to Bal
A2: Universal Journal | G2: Universal Balance
A3: Field Contents | B3: fFieldName | D3: Field Type | E3: Data Source | G3: Field Contents | H3: fFieldName | J3: Field Type | K3: Data Source
A4: Instrument ID | B4: instID | C4: Unique ID | D4: Number | E4: Unique Instrument ID | G4: Instrument ID | H4: instID | I4: Unique ID | J4: Number | K4: Unique Instrument ID
A5: Business Event / Journal ID | B5: jrnlID | C5: Unique ID | D5: Number | E5: Fiscal Date File count + Record count | G5: Balance ID | H5: balID | I5: Unique ID | J5: Number | K5: File count + Record count
A6: Jrnl Line No | B6: jrnlLineID | C6: Unique ID | D6: Number | E6: Increment
A7: Journal / Event Description | B7: jrnlDescript | C7: Input Field | D7: Text | E7: Mapped Field From File
A8: Ledger | B8: ledgerID | C8: Constant | D8: Text | E8: Actual-Historical | G8: Ledger | H8: ledgerID | I8: Constant | J8: Text | K8: Actual-Historical
A9: Jrnl Type | B9: jrnlType | C9: Constant | D9: Text | E9: Financial | G9: Jrnl Type | H9: jrnlType | I9: Constant | J9: Text | K9: Financial, FINADJ
A10: Book-code / Basis | B10: bookCodeID | C10: Constant | D10: Text | E10: Shared-3rd-Party | G10: Book-code / Basis | H10: bookCodeID | I10: Constant | J10: Text | K10: Shared-3rd-Party
A11: Legal Entity (CO. / Owner) | B11: legalEntityID | C11: Xref Key | D11: Number | E11: Mapped Field From File | G11: Legal Entity (CO. / Owner) | H11: legalEntityID | I11: Xref Key | J11: Number | K11: Mapped Field From File
A12: Center ID | B12: centerID | C12: Xref Key | D12: Number | E12: Mapped Field From File | G12: Center ID | H12: centerID | I12: Xref Key | J12: Number | K12: Mapped Field From File
A13: Project ID | B13: projectID | C13: Xref Key | D13: Number | E13: Mapped Field From File | G13: Project ID | H13: projectID | I13: Xref Key | J13: Number | K13: Mapped Field From File
A14: Product / Material ID | B14: productID | C14: Constant | D14: Text | G14: Product / Material ID | H14: productID | I14: Constant | J14: Text
A15: Nominal Account | B15: accountID | C15: Xref Key | D15: Number | E15: Mapped Field From File | G15: Nominal Account | H15: accountID | I15: Xref Key | J15: Number | K15: Mapped Field From File
A16: Curr. Code Source | B16: currencyCodeSourceID | C16: Constant | D16: Text | E16: USD | G16: Curr. Code Source | H16: currencyCodeSourceID | I16: Constant | J16: Text | K16: USD
A17: Currency Type Code Source | B17: currencyTypeCodeSourceID | C17: Constant | D17: Text | E17: TXN | G17: Currency Type Code Source | H17: currencyTypeCodeSourceID | I17: Constant | J17: Text | K17: TXN
A18: Curr. Code Target | B18: currencyCodeTargetID | C18: Constant | D18: Text | E18: USD | G18: Curr. Code Target | H18: currencyCodeTargetID | I18: Constant | J18: Text | K18: USD
A19: Currency Type Code Target | B19: currencyTypeCodeTargetID | C19: Constant | D19: Text | E19: BASE-LE | G19: Currency Type Code Target | H19: currencyTypeCodeTargetID | I19: Constant | J19: Text | K19: BASE-LE
A20: Transaction Amount | B20: transAmount | C20: Value | D20: Number | E20: Mapped Field From File | G20: Fiscal Year | H20: fiscalYear | I20: Derived | J20: Date | K20: Year from Fiscal Date
A21: Fiscal Period | B21: fiscalPeriod | C21: Derived | D21: Date | E21: Date from File Name | G21: Transaction Amount | H21: transAmount | I21: Value | J21: Number | K21: Mapped Field From File
A22: Acctg. Date | B22: acctDate | C22: Derived | D22: Date | E22: Date from File or File Name
A23: Transaction Date | B23: transDate | C23: Input Field | D23: Date | E23: Mapped Field From File
A24: Direct vs. Offset Flag | B24: dirVsOffsetFlg | C24: Constant | D24: Flag | E24: Y/N based upon record
A25: Reconciliable Flag | B25: reconcileFlg | C25: Constant | D25: Flag | E25: N
A26: Adjustment Flag | B26: adjustFlg | C26: Constant | D26: Flag | E26: N
A27: Movement Flag | B27: movementFlg | C27: Constant | D27: Flag | E27: N | G27: Movement Flag | H27: movementFlg | I27: Constant | J27: Flag | K27: N
A28: Unit of Measure | B28: unitOfMeasure | C28: Constant | D28: Text | E28: Financial | G28: Unit of Measure | H28: unitOfMeasure | I28: Constant | J28: Text | K28: Financial
A29: Statistical Amount | B29: statisticAmount | C29: Constant | D29: Number | E29: 0 | G29: Statistical Amount | H29: statisticAmount | I29: Constant | J29: Number | K29: 0
A30: Audit Trial Extension ID | B30: extensionIDAuditTrail | C30: Xref Key | D30: Number | E30: default 0, not currently used
A31: Source Extension ID | B31: extensionIDSource | C31: Xref Key | D31: Number | E31: default 0, not currently used
A32: Classification Extension ID | B32: extensionIDClass | C32: Xref Key | D32: Number | E32: default 0, not currently used
A33: Date Extension ID | B33: extensionIDDates | C33: Xref Key | D33: Number | E33: default 0, not currently used
A34: Other Customization Ext ID | B34: extensionIDCustom | C34: Xref Key | D34: Number | E34: default 0, not currently used
